Workbook

Sheet Raw_Data
A1: Order_ID | B1: Order_Date | C1: Brand | D1: Model | E1: Segment | F1: City | G1: Sales_Channel | H1: Payment_Method | I1: Color | J1: Salesperson_ID | K1: Units_Sold | L1: Unit_Price | M1: Discount_Pct | N1: Gross_Sales | O1: Discount_Amount | P1: Net_Sales | Q1: Battery_kWh | R1: Range_km | S1: Customer_Rating | T1: Delivery_Days | U1: Warranty_Years
A2: EV10001 | B2: 46006 | C2: Revolt | D2: RV1 | E2: Premium | F2: Chennai | G2: Online | H2: Finance | I2: Green | J2: SP-002 | K2: 1 | L2: 125898 | M2: 0.08 | N2: 125898 | O2: 10071.84 | P2: 115826.16 | Q2: 3 | R2: 162 | S2: 3.7 | T2: 6 | U2: 5
A3: EV10002 | B3: 45934 | C3: Vida | D3: V2 | E3: Premium | F3: Bengaluru | G3: Fleet | H3: EMI | I3: Red | J3: SP-025 | K3: 2 | L3: 112819 | M3: 0.021 | N3: 225638 | O3: 4738.4 | P3: 220899.6 | Q3: 2 | R3: 116 | S3: 4.4 | T3: 13 | U3: 5
A4: EV10003 | B4: 45964 | C4: TVS | D4: iQube | E4: Premium | F4: Hyderabad | G4: Fleet | H4: EMI | I4: Red | J4: SP-007 | K4: 2 | L4: 125383 | M4: 0.021 | N4: 250766 | O4: 5266.09 | P4: 245499.91 | Q4: 5 | R4: 175 | S4: 4.6 | T4: 11 | U4: 2
A5: EV10004 | B5: 45921 | C5: Bajaj | D5: Chetak Premium | E5: Commuter | F5: Mumbai | G5: Online | H5: Finance | I5: White | J5: SP-030 | K5: 1 | L5: 160095 | M5: 0.046 | N5: 160095 | O5: 7364.37 | P5: 152730.63 | Q5: 4 | R5: 184 | S5: 3.2 | T5: 11 | U5: 3
A6: EV10005 | B6: 46008 | C6: Bajaj | D6: Chetak Urbane | E6: Commuter | F6: Ahmedabad | G6: Online | H6: Cash | I6: Red | J6: SP-028 | K6: 4 | L6: 114286 | M6: 0.04 | N6: 457144 | O6: 18285.76 | P6: 438858.24 | Q6: 2 | R6: 133 | S6: 3.4 | T6: 3 | U6: 5
A7: EV10006 | B7: 45698 | C7: Bajaj | D7: Chetak Premium | E7: Commuter | F7: Ahmedabad | G7: Corporate | H7: EMI | I7: Black | J7: SP-027 | K7: 1 | L7: 144470 | M7: 0.022 | N7: 144470 | O7: 3178.34 | P7: 141291.66 | Q7: 3 | R7: 145 | S7: 3.7 | T7: 12 | U7: 5
A8: EV10007 | B8: 45888 | C8: Hero Electric | D8: Photon | E8: Performance | F8: Ahmedabad | G8: Online | H8: EMI | I8: Blue | J8: SP-001 | K8: 2 | L8: 122830 | M8: 0.105 | N8: 245660 | O8: 25794.3 | P8: 219865.7 | Q8: 3 | R8: 161 | S8: 3.8 | T8: 9 | U8: 2
A9: EV10008 | B9: 45788 | C9: TVS | D9: iQube | E9: Performance | F9: Kolkata | G9: Dealer | H9: Cash | I9: Red | J9: SP-030 | K9: 3 | L9: 127322 | M9: 0.097 | N9: 381966 | O9: 37050.7 | P9: 344915.3 | Q9: 3 | R9: 132 | S9: 4.5 | T9: 11 | U9: 2
A10: EV10009 | B10: 45888 | C10: Hero Electric | D10: Optima | E10: Commuter | F10: Jaipur | G10: Dealer | H10: Finance | I10: Red | J10: SP-028 | K10: 1 | L10: 109806 | M10: 0.043 | N10: 109806 | O10: 4721.66 | P10: 105084.34 | Q10: 2 | R10: 136 | S10: 3.9 | T10: 3 | U10: 3
A11: EV10010 | B11: 45997 | C11: Bajaj | D11: Chetak Urbane | E11: Premium | F11: Jaipur | G11: Fleet | H11: Cash | I11: Black | J11: SP-003 | K11: 4 | L11: 121860 | M11: 0.101 | N11: 487440 | O11: 49231.44 | P11: 438208.56 | Q11: 5 | R11: 191 | S11: 4 | T11: 10 | U11: 5
A12: EV10011 | B12: 45794 | C12: Revolt | D12: RV1 | E12: Commuter | F12: Delhi | G12: Online | H12: Finance | I12: White | J12: SP-003 | K12: 1 | L12: 124432 | M12: 0.047 | N12: 124432 | O12: 5848.3 | P12: 118583.7 | Q12: 3 | R12: 158 | S12: 3.8 | T12: 9 | U12: 2
A13: EV10012 | B13: 45770 | C13: Ather | D13: 450X | E13: Premium | F13: Mumbai | G13: Dealer | H13: Finance | I13: Green | J13: SP-023 | K13: 5 | L13: 141715 | M13: 0.118 | N13: 708575 | O13: 83611.85 | P13: 624963.15 | Q13: 3 | R13: 163 | S13: 4 | T13: 2 | U13: 5
... A23: EV10022 | B23: 45921 | C23: Bajaj | D23: Chetak Premium | E23: Premium | F23: Bengaluru | G23: Dealer | H23: Finance | I23: Green | J23: SP-029 | K23: 2 | L23: 157711 | M23: 0.109 | N23: 315422 | O23: 34381 | P23: 281041 | Q23: 3 | R23: 154 | S23: 4 | T23: 8 | U23: 5
A24: EV10023 | B24: 45715 | C24: Ampere | D24: Primus | E24: Performance | F24: Hyderabad | G24: Online | H24: Cash | I24: Red | J24: SP-030 | K24: 1 | L24: 141784 | M24: 0.102 | N24: 141784 | O24: 14461.97 | P24: 127322.03 | Q24: 3 | R24: 164 | T24: 6 | U24: 2
A25: EV10024 | B25: 45968 | C25: Revolt | D25: RV400 | E25: Performance | F25: Kochi | G25: Dealer | H25: Finance | I25: Grey | J25: SP-030 | K25: 1 | L25: 134201 | M25: 0.117 | N25: 134201 | O25: 15701.52 | P25: 118499.48 | Q25: 4 | R25: 180 | S25: 3.9 | T25: 4 | U25: 3
A26: EV10025 | B26: 45786 | C26: Revolt | D26: RV400 | E26: Commuter | F26: Kolkata | G26: Fleet | H26: EMI | I26: Grey | J26: SP-022 | K26: 1 | L26: 134666 | M26: 0.045 | N26: 134666 | O26: 6059.97 | P26: 128606.03 | Q26: 4 | R26: 193 | S26: 4.7 | T26: 6 | U26: 2
A27: EV10026 | B27: 45733 | C27: Hero Electric | D27: Optima | E27: Premium | F27: Chennai | G27: Corporate | H27: Finance | I27: White | J27: SP-022 | K27: 2 | L27: 101032 | M27: 0.032 | N27: 202064 | O27: 6466.05 | P27: 195597.95 | Q27: 3 | R27: 172 | S27: 4.4 | T27: 5 | U27: 2
A28: EV10027 | B28: 45947 | C28: Hero Electric | D28: Photon | E28: Premium | F28: Delhi | G28: Fleet | H28: EMI | I28: Red | J28: SP-024 | K28: 1 | L28: 108346 | M28: 0.113 | N28: 108346 | O28: 12243.1 | P28: 96102.9 | Q28: 4 | R28: 205 | S28: 4.3 | T28: 9 | U28: 5
A29: EV10028 | B29: 45820 | C29: Bajaj | D29: Chetak Urbane | E29: Commuter | F29: Mumbai | G29: Dealer | H29: EMI | I29: White | J29: SP-003 | K29: 2 | L29: 120498 | M29: 0.075 | N29: 240996 | O29: 18074.7 | P29: 222921.3 | Q29: 5 | R29: 205 | S29: 4.1 | T29: 11 | U29: 5
A30: EV10029 | B30: 45747 | C30: Revolt | D30: RV400 | E30: Commuter | F30: Ahmedabad | G30: Fleet | H30: Cash | I30: Grey | J30: SP-029 | K30: 1 | L30: 148159 | M30: 0.022 | N30: 148159 | O30: 3259.5 | P30: 144899.5 | Q30: 4 | R30: 174 | S30: 3.9 | T30: 6 | U30: 3
A31: EV10030 | B31: 46014 | C31: Ather | D31: 450S | E31: Premium | F31: Chennai | G31: Fleet | H31: Cash | I31: Grey | J31: SP-023 | K31: 3 | L31: 136884 | M31: 0.119 | N31: 410652 | O31: 48867.59 | P31: 361784.41 | Q31: 3 | R31: 179 | S31: 3.8 | T31: 9 | U31: 5
A32: EV10031 | B32: 46018 | C32: Ather | D32: Rizta | E32: Commuter | F32: Bengaluru | G32: Fleet | H32: Cash | I32: Red | J32: SP-014 | K32: 1 | L32: 136998 | M32: 0.07 | N32: 136998 | O32: 9589.86 | P32: 127408.14 | Q32: 3 | R32: 156 | S32: 4 | T32: 5 | U32: 2
A33: EV10032 | B33: 45709 | C33: Revolt | D33: RV1 | E33: Performance | F33: Jaipur | G33: Corporate | H33: Cash | I33: Grey | J33: SP-010 | K33: 2 | L33: 123414 | M33: 0.065 | N33: 246828 | O33: 16043.82 | P33: 230784.18 | Q33: 3 | R33: 178 | S33: 3.6 | T33: 5 | U33: 2
A34: EV10033 | B34: 45880 | C34: Ola Electric | D34: S1 X | E34: Premium | F34: Ahmedabad | G34: Online | H34: Cash | I34: White | J34: SP-027 | K34: 1 | L34: 109534 | M34: 0.075 | N34: 109534 | O34: 8215.05 | P34: 101318.95 | Q34: 4 | R34: 183 | S34: 4.1 | T34: 7 | U34: 5
A35: EV10034 | B35: 45662 | C35: Ola Electric | D35: S1 Air | E35: Commuter | F35: Hyderabad | G35: Fleet | H35: Finance | I35: Red | J35: SP-019 | K35: 2 | L35: 111854 | M35: 0.078 | N35: 223708 | O35: 17449.22 | P35: 206258.78 | Q35: 5 | R35: 196 | S35: 4.3 | T35: 8 | U35: 2
A36: EV10035 | B36: 45839 | C36: Hero Electric | D36: Photon | E36: Performance | F36: Jaipur | G36: Corporate | H36: Cash | I36: Blue | J36: SP-013 | K36: 2 | L36: 112104 | M36: 0.053 | N36: 224208 | O36: 11883.02 | P36: 212324.98 | Q36: 3 | R36: 157 | S36: 3.4 | T36: 11 | U36: 2
... A97: EV10096 | B97: 46001 | C97: Hero Electric | D97: Optima | E97: Commuter | F97: Jaipur | G97: Dealer | H97: Finance | I97: Black | J97: SP-008 | K97: 1 | L97: 113169 | M97: 0.035 | N97: 113169 | O97: 3960.92 | P97: 109208.08 | Q97: 3 | R97: 152 | S97: 4.8 | T97: 7 | U97: 5
A98: EV10097 | B98: 45836 | C98: TVS | D98: X | E98: Premium | F98: Ahmedabad | G98: Fleet | H98: Finance | I98: Red | J98: SP-001 | K98: 1 | L98: 175299 | M98: 0.119 | N98: 175299 | O98: 20860.58 | P98: 154438.42 | Q98: 3 | R98: 192 | T98: 5 | U98: 2
A99: EV10098 | B99: 45946 | C99: ola electric | D99: S1 Pro | E99: Performance | F99: Delhi | G99: Fleet | H99: EMI | I99: Grey | J99: SP-003 | K99: 4 | L99: 133217 | M99: 0.102 | N99: 532868 | O99: 54352.54 | P99: 478515.46 | Q99: 3 | R99: 171 | S99: 3.7 | T99: 3 | U99: 3
A100: EV10099 | B100: 45666 | C100: TVS | D100: X | E100: Performance | F100: Kolkata | G100: Corporate | H100: Finance | I100: White | J100: SP-022 | K100: 5 | L100: 170509 | M100: 0.074 | N100: 852545 | O100: 63088.33 | P100: 789456.67 | Q100: 4 | R100: 186 | S100: 4.4 | T100: 5 | U100: 3
A101: EV10100 | B101: 45660 | C101: Ola Electric | D101: S1 X | E101: Performance | F101: Kochi | G101: Corporate | H101: EMI | I101: Green | J101: SP-004 | K101: 1 | L101: 101110 | M101: 0.064 | N101: 101110 | O101: 6471.04 | P101: 94638.96 | Q101: 4 | R101: 202 | S101: 4.6 | T101: 10 | U101: 2
A102: EV10101 | B102: 45878 | C102: Hero Electric | D102: Photon | E102: Performance | F102: Bengaluru | G102: Fleet | H102: Finance | I102: Blue | J102: SP-003 | K102: 3 | L102: 118705 | M102: 0.07 | N102: 356115 | O102: 24928.05 | P102: 331186.95 | Q102: 4 | R102: 170 | S102: 4.4 | T102: 9 | U102: 2
A103: EV10102 | B103: 45864 | C103: Hero Electric | D103: Optima | E103: Premium | F103: Delhi | G103: Corporate | H103: Cash | I103: Red | J103: SP-026 | K103: 1 | L103: 105500 | M103: 0.107 | N103: 105500 | O103: 11288.5 | P103: 94211.5 | Q103: 4 | R103: 176 | S103: 4.8 | T103: 5 | U103: 3
A104: EV10103 | B104: 45885 | C104: Hero Electric | D104: Photon | E104: Commuter | F104: Mumbai | G104: Fleet | H104: Cash | I104: Black | J104: SP-003 | K104: 4 | L104: 122601 | M104: 0.062 | N104: 490404 | O104: 30405.05 | P104: 459998.95 | Q104: 3 | R104: 173 | S104: 4.2 | T104: 13 | U104: 5
A105: EV10104 | B105: 45744 | C105: Ola Electric | D105: S1 Air | E105: Performance | F105: Ahmedabad | G105: Corporate | H105: Cash | I105: Red | J105: SP-002 | K105: 2 | L105: 114102 | M105: 0.071 | N105: 228204 | O105: 16202.48 | P105: 212001.52 | Q105: 3 | R105: 162 | S105: 3.8 | T105: 7 | U105: 2
A106: EV10105 | B106: 45802 | C106: Revolt | D106: RV1 | E106: Performance | F106: Kochi | G106: Corporate | H106: Finance | I106: Green | J106: SP-016 | K106: 1 | L106: 129086 | M106: 0.046 | N106: 129086 | O106: 5937.96 | P106: 123148.04 | Q106: 4 | R106: 195 | S106: 3.8 | T106: 9 | U106: 2
A107: EV10106 | B107: 45923 | C107: Ola Electric | D107: S1 Pro | E107: Performance | F107: Chennai | G107: Fleet | H107: Cash | I107: Black | J107: SP-017 | K107: 2 | L107: 134456 | M107: 0.065 | N107: 268912 | O107: 17479.28 | P107: 251432.72 | Q107: 4 | R107: 166 | S107: 3.4 | T107: 12 | U107: 2
A108: EV10107 | B108: 45969 | C108: Vida | D108: V2 | E108: Commuter | F108: Delhi | G108: Corporate | H108: EMI | I108: Green | J108: SP-005 | K108: 2 | L108: 116771 | M108: 0.041 | N108: 233542 | O108: 9575.22 | P108: 223966.78 | Q108: 2 | R108: 145 | S108: 4.1 | T108: 6 | U108: 3
A109: EV10108 | B109: 45982 | C109: Hero Electric | D109: Optima | E109: Premium | F109: Jaipur | G109: Corporate | H109: EMI | I109: Blue | J109: SP-018 | K109: 1 | L109: 107294 | M109: 0.089 | N109: 107294 | O109: 9549.17 | P109: 97744.83 | Q109: 3 | R109: 187 | S109: 4 | T109: 3 | U109: 2
A110: EV10109 | B110: 45951 | C110: Revolt | D110: RV1 | E110: Commuter | F110: Kolkata | G110: Fleet | H110: Cash | I110: Green | J110: SP-005 | K110: 1 | L110: 113303 | M110: 0.051 | N110: 113303 | O110: 5778.45 | P110: 107524.55 | Q110: 4 | R110: 189 | S110: 3.6 | T110: 3 | U110: 2
... A162: EV10161 | B162: 46010 | C162: Ather | D162: Rizta | E162: Commuter | F162: Mumbai | G162: Corporate | H162: Cash | I162: Grey | J162: SP-024 | K162: 1 | L162: 142453 | M162: 0.041 | N162: 142453 | O162: 5840.57 | P162: 136612.43 | Q162: 3 | R162: 169 | S162: 4 | T162: 7 | U162: 5
A163: EV10162 | B163: 45788 | C163: Ola Electric | D163: S1 Air | E163: Commuter | F163: Bengaluru | G163: Corporate | H163: Finance | I163: White | J163: SP-011 | K163: 4 | L163: 116559 | N163: 466236 | O163: 20514.38 | P163: 445721.62 | Q163: 2 | R163: 148 | S163: 3.9 | T163: 4 | U163: 3
A164: EV10163 | B164: 45833 | C164: Ather | D164: Rizta | E164: Performance | F164: Pune | G164: Dealer | H164: Cash | I164: Blue | J164: SP-004 | K164: 2 | L164: 140849 | M164: 0.101 | N164: 281698 | O164: 28451.5 | P164: 253246.5 | Q164: 5 | R164: 194 | S164: 4.2 | T164: 4 | U164: 5
A165: EV10164 | B165: 45960 | C165: Ola Electric | D165: S1 Pro | E165: Performance | F165: Jaipur | G165: Corporate | H165: Cash | I165: White | J165: SP-019 | K165: 1 | L165: 135767 | M165: 0.023 | N165: 135767 | O165: 3122.64 | P165: 132644.36 | Q165: 3 | R165: 170 | S165: 4.2 | T165: 13 | U165: 2
A166: EV10165 | B166: 45908 | C166: Ather | D166: 450S | E166: Premium | F166: Hyderabad | G166: Dealer | H166: Cash | I166: Green | J166: SP-026 | K166: 1 | L166: 125277 | M166: 0.059 | N166: 125277 | O166: 7391.34 | P166: 117885.66 | Q166: 3 | R166: 157 | S166: 3.5 | T166: 4 | U166: 5
A167: EV10166 | B167: 45807 | C167: Ampere | D167: Magnus EX | E167: Performance | F167: Hyderabad | G167: Online | H167: Finance | I167: Grey | J167: SP-029 | K167: 4 | L167: 107900 | M167: 0.111 | N167: 431600 | O167: 47907.6 | P167: 383692.4 | Q167: 4 | R167: 192 | S167: 3.9 | T167: 13 | U167: 5
A168: EV10167 | B168: 45943 | C168: Bajaj | D168: Chetak Urbane | E168: Commuter | F168: Pune | G168: Dealer | H168: EMI | I168: Grey | J168: SP-030 | K168: 1 | L168: 122328 | M168: 0.048 | N168: 122328 | O168: 5871.74 | P168: 116456.26 | Q168: 4 | R168: 189 | S168: 4.8 | T168: 12 | U168: 3
A169: EV10168 | B169: 45925 | C169: Ather | D169: 450S | E169: Commuter | F169: Jaipur | G169: Fleet | H169: EMI | I169: Black | J169: SP-002 | K169: 2 | L169: 140316 | M169: 0.106 | N169: 280632 | O169: 29746.99 | P169: 250885.01 | Q169: 4 | R169: 170 | S169: 4.2 | T169: 14 | U169: 2
A170: EV10169 | B170: 45722 | C170: Vida | D170: V2 | E170: Commuter | F170: Pune | G170: Fleet | H170: Cash | I170: Blue | J170: SP-006 | K170: 1 | L170: 114094 | M170: 0.028 | N170: 114094 | O170: 3194.63 | P170: 110899.37 | Q170: 5 | R170: 186 | T170: 4 | U170: 3
A171: EV10170 | B171: 45814 | C171: Bajaj | D171: Chetak Premium | E171: Commuter | F171: Delhi | G171: Fleet | H171: EMI | I171: Green | J171: SP-006 | K171: 2 | L171: 155204 | M171: 0.033 | N171: 310408 | O171: 10243.46 | P171: 300164.54 | Q171: 3 | R171: 153 | S171: 3.7 | T171: 12 | U171: 5
A172: EV10171 | B172: 45867 | C172: Ampere | D172: Magnus EX | E172: Performance | F172: Hyderabad | G172: Fleet | H172: Cash | I172: Grey | J172: SP-029 | K172: 1 | L172: 110676 | M172: 0.025 | N172: 110676 | O172: 2766.9 | P172: 107909.1 | Q172: 3 | R172: 161 | S172: 3.2 | T172: 9 | U172: 3
A173: EV10172 | B173: 45959 | C173: Ampere | D173: Magnus EX | E173: Premium | F173: Jaipur | G173: Dealer | H173: Cash | I173: Black | J173: SP-009 | K173: 1 | L173: 116233 | M173: 0.104 | N173: 116233 | O173: 12088.23 | P173: 104144.77 | Q173: 3 | R173: 135 | S173: 3.5 | T173: 11 | U173: 5
A174: EV10173 | B174: 45964 | C174: Ather | D174: 450X | E174: Performance | F174: Ahmedabad | G174: Fleet | H174: Cash | I174: Grey | J174: SP-013 | K174: 4 | L174: 147968 | M174: 0.023 | N174: 591872 | O174: 13613.06 | P174: 578258.94 | Q174: 4 | R174: 181 | S174: 3.8 | T174: 14 | U174: 2
A175: EV10174 | B175: 45897 | C175: Bajaj | D175: Chetak Premium | E175: Premium | F175: Mumbai | G175: Online | H175: Finance | I175: Black | J175: SP-004 | K175: 1 | L175: 156087 | M175: 0.115 | N175: 156087 | O175: 17950.01 | P175: 138136.99 | Q175: 4 | R175: 191 | S175: 4.3 | T175: 2 | U175: 5
A176: EV10175 | B176: 45804 | C176: Ola Electric | D176: S1 Pro | E176: Commuter | F176: Jaipur | G176: Online | H176: Finance | I176: Blue | J176: SP-011 | K176: 2 | L176: 142371 | M176: 0.11 | N176: 284742 | O176: 31321.62 | P176: 253420.38 | Q176: 3 | R176: 177 | S176: 3.7 | T176: 3 | U176: 5
A177: EV10176 | B177: 45867 | C177: Hero Electric | D177: Photon | E177: Performance | F177: Ahmedabad | G177: Online | H177: Cash | I177: Black | J177: SP-030 | K177: 1 | L177: 109963 | M177: 0.035 | N177: 109963 | O177: 3848.71 | P177: 106114.29 | Q177: 3 | R177: 179 | S177: 4.4 | T177: 14 | U177: 3
A178: EV10177 | B178: 45892 | C178: Bajaj | D178: Chetak Premium | E178: Premium | F178: Chennai | G178: Online | H178: EMI | I178: White | J178: SP-004 | K178: 1 | L178: 153121 | M178: 0.024 | N178: 153121 | O178: 3674.9 | P178: 149446.1 | Q178: 3 | R178: 140 | S178: 4.4 | T178: 8 | U178: 2
A179: EV10178 | B179: 45730 | C179: TVS | D179: iQube | E179: Performance | F179: Ahmedabad | G179: Corporate | H179: Finance | I179: Blue | J179: SP-025 | K179: 1 | L179: 131307 | M179: 0.065 | N179: 131307 | O179: 8534.95 | P179: 122772.05 | Q179: 4 | R179: 185 | S179: 4.2 | T179: 10 | U179: 5
A180: EV10179 | B180: 45824 | C180: Ampere | D180: Primus | E180: Performance | F180: Delhi | G180: Dealer | H180: Finance | I180: Grey | J180: SP-008 | K180: 2 | L180: 144478 | M180: 0.085 | N180: 288956 | O180: 24561.26 | P180: 264394.74 | Q180: 2 | R180: 148 | S180: 3.1 | T180: 3 | U180: 5
A181: EV10180 | B181: 45978 | C181: Ola Electric | D181: S1 Air | E181: Performance | F181: Pune | G181: Corporate | H181: EMI | I181: White | J181: SP-019 | K181: 1 | L181: 110794 | M181: 0.117 | N181: 110794 | O181: 12962.9 | P181: 97831.1 | Q181: 3 | R181: 164 | S181: 4.3 | T181: 14 | U181: 3
A182: EV10181 | B182: 45972 | C182: Ola Electric | D182: S1 Air | E182: Premium | F182: Hyderabad | G182: Online | H182: Cash | I182: Black | J182: SP-029 | K182: 1 | L182: 115954 | M182: 0.033 | N182: 115954 | O182: 3826.48 | P182: 112127.52 | Q182: 5 | R182: 183 | S182: 3.4 | T182: 4 | U182: 5
... A185: EV10184 | B185: 45930 | C185: Ola Electric | D185: S1 X | E185: Commuter | F185: Chennai | G185: Fleet | H185: Finance | I185: Blue | J185: SP-027 | K185: 2 | L185: 103117 | M185: 0.053 | N185: 206234 | O185: 10930.4 | P185: 195303.6 | Q185: 4 | R185: 202 | S185: 4 | T185: 9 | U185: 2
A186: EV10185 | B186: 45924 | C186: Hero Electric | D186: Photon | E186: Premium | F186: Kochi | G186: Fleet | H186: Finance | I186: Black | J186: SP-019 | K186: 1 | L186: 115481 | M186: 0.024 | N186: 115481 | O186: 2771.54 | P186: 112709.46 | Q186: 4 | R186: 173 | T186: 9 | U186: 2
A187: EV10186 | B187: 45961 | C187: TVS | D187: X | E187: Performance | F187: Jaipur | G187: Corporate | H187: Finance | I187: Black | J187: SP-019 | K187: 1 | L187: 188216 | M187: 0.069 | N187: 188216 | O187: 12986.9 | P187: 175229.1 | Q187: 3 | R187: 203 | S187: 3.5 | T187: 9 | U187: 5
A188: EV10187 | B188: 45876 | C188: Hero Electric | D188: Photon | E188: Performance | F188: Pune | G188: Corporate | H188: EMI | I188: Grey | J188: SP-013 | K188: 1 | L188: 121423 | M188: 0.096 | N188: 121423 | O188: 11656.61 | P188: 109766.39 | Q188: 4 | R188: 195 | S188: 4 | T188: 9 | U188: 5
A189: EV10188 | B189: 45846 | C189: Revolt | D189: RV1 | E189: Commuter | F189: Mumbai | G189: Dealer | H189: EMI | I189: Green | J189: SP-025 | K189: 4 | L189: 113121 | M189: 0.068 | N189: 452484 | O189: 30768.91 | P189: 421715.09 | Q189: 4 | R189: 193 | S189: 4.6 | T189: 11 | U189: 3
A190: EV10189 | B190: 45820 | C190: Ampere | D190: Magnus EX | E190: Commuter | G190: Corporate | H190: Cash | I190: Red | J190: SP-003 | K190: 5 | L190: 113823 | M190: 0.103 | N190: 569115 | O190: 58618.84 | P190: 510496.16 | Q190: 3 | R190: 170 | S190: 4.4 | T190: 6 | U190: 2
A191: EV10190 | B191: 45761 | C191: Ola Electric | D191: S1 X | E191: Premium | F191: Bengaluru | G191: Corporate | H191: Finance | I191: White | J191: SP-008 | K191: 1 | L191: 109330 | M191: 0.048 | N191: 109330 | O191: 5247.84 | P191: 104082.16 | Q191: 4 | R191: 207 | S191: 4.5 | T191: 14 | U191: 2
A192: EV10191 | B192: 45819 | C192: Ather | D192: Rizta | E192: Performance | F192: Bengaluru | G192: Fleet | H192: EMI | I192: Green | J192: SP-024 | K192: 3 | L192: 140263 | M192: 0.025 | N192: 420789 | O192: 10519.73 | P192: 410269.27 | Q192: 2 | R192: 126 | S192: 3.8 | T192: 13 | U192: 3
A193: EV10192 | B193: 45684 | C193: Ampere | D193: Magnus EX | E193: Performance | F193: Delhi | G193: Corporate | H193: EMI | I193: Green | J193: SP-010 | K193: 1 | L193: 112382 | M193: 0.104 | N193: 112382 | O193: 11687.73 | P193: 100694.27 | Q193: 4 | R193: 177 | S193: 3.5 | T193: 10 | U193: 3
A194: EV10193 | B194: 45709 | C194: Ola Electric | D194: S1 Air | E194: Performance | F194: Kolkata | G194: Fleet | H194: Finance | I194: Red | J194: SP-023 | K194: 2 | L194: 116573 | M194: 0.066 | N194: 233146 | O194: 15387.64 | P194: 217758.36 | Q194: 3 | R194: 150 | S194: 3.6 | T194: 5 | U194: 2
A195: EV10194 | B195: 45947 | C195: Revolt | D195: RV1 | E195: Commuter | F195: Kolkata | G195: Fleet | H195: Finance | I195: Black | J195: SP-006 | K195: 1 | L195: 123376 | M195: 0.025 | N195: 123376 | O195: 3084.4 | P195: 120291.6 | Q195: 4 | R195: 174 | S195: 4.1 | T195: 7 | U195: 3
A196: EV10195 | B196: 45977 | C196: Hero Electric | D196: Photon | E196: Performance | F196: Bengaluru | G196: Dealer | H196: EMI | I196: Black | J196: SP-006 | K196: 1 | L196: 109740 | M196: 0.056 | N196: 109740 | O196: 6145.44 | P196: 103594.56 | Q196: 3 | R196: 158 | S196: 4.5 | T196: 5 | U196: 3
A197: EV10196 | B197: 45836 | C197: Vida | D197: V2 | E197: Performance | F197: Chennai | G197: Dealer | H197: EMI | I197: Grey | J197: SP-005 | K197: 1 | L197: 113980 | M197: 0.069 | N197: 113980 | O197: 7864.62 | P197: 106115.38 | Q197: 3 | R197: 181 | S197: 4.5 | T197: 11 | U197: 5
A198: EV10197 | B198: 45930 | C198: Ather | D198: Rizta | E198: Performance | F198: Mumbai | G198: Fleet | H198: Finance | I198: Blue | J198: SP-012 | K198: 2 | L198: 144741 | M198: 0.047 | N198: 289482 | O198: 13605.65 | P198: 275876.35 | Q198: 3 | R198: 163 | S198: 3.7 | T198: 8 | U198: 2
A199: EV10198 | B199: 45670 | C199: Ather | D199: Rizta | E199: Commuter | F199: Hyderabad | G199: Dealer | H199: EMI | I199: Grey | J199: SP-013 | K199: 1 | L199: 142439 | M199: 0.105 | N199: 142439 | O199: 14956.09 | P199: 127482.91 | Q199: 3 | R199: 159 | S199: 5 | T199: 9 | U199: 3
A200: EV10199 | B200: 45873 | C200: Ola Electric | D200: S1 Pro | E200: Commuter | F200: Hyderabad | G200: Dealer | H200: EMI | I200: Blue | J200: SP-013 | K200: 5 | L200: 134064 | M200: 0.094 | N200: 670320 | O200: 63010.08 | P200: 607309.92 | Q200: 5 | R200: 201 | S200: 3.9 | T200: 7 | U200: 3
A201: EV10200 | B201: 45775 | C201: Ather | D201: 450X | E201: Commuter | F201: Hyderabad | G201: Online | H201: Finance | I201: Blue | J201: SP-025 | K201: 3 | L201: 147339 | M201: 0.03 | N201: 442017 | O201: 13260.51 | P201: 428756.49 | Q201: 4 | R201: 185 | S201: 4 | T201: 3 | U201: 3
A202: EV10201 | B202: 45759 | C202: TVS | D202: iQube | E202: Performance | F202: Delhi | G202: Fleet | H202: Finance | I202: Red | J202: SP-027 | K202: 2 | L202: 127914 | N202: 255828 | O202: 5372.39 | P202: 250455.61 | Q202: 3 | R202: 164 | S202: 4.3 | T202: 7 | U202: 2
A203: EV10202 | B203: 45827 | C203: Ampere | D203: Magnus EX | E203: Premium | F203: Chennai | G203: Fleet | H203: Cash | I203: Red | J203: SP-015 | K203: 3 | L203: 115830 | M203: 0.032 | N203: 347490 | O203: 11119.68 | P203: 336370.32 | Q203: 3 | R203: 165 | S203: 4.8 | T203: 5 | U203: 2
A204: EV10203 | B204: 45817 | C204: TVS | D204: iQube | E204: Commuter | F204: Mumbai | G204: Online | H204: Cash | I204: Red | J204: SP-023 | K204: 4 | L204: 131205 | M204: 0.098 | N204: 524820 | O204: 51432.36 | P204: 473387.64 | Q204: 3 | R204: 144 | S204: 3.7 | T204: 4 | U204: 2
A205: EV10204 | B205: 45661 | C205: Bajaj | D205: Chetak Urbane | E205: Commuter | F205: Delhi | G205: Corporate | H205: Finance | I205: Red | J205: SP-007 | K205: 5 | L205: 128637 | M205: 0.099 | N205: 643185 | O205: 63675.32 | P205: 579509.68 | Q205: 5 | R205: 206 | S205: 4.1 | T205: 13 | U205: 3
A206: EV10205 | B206: 45683 | C206: Ola Electric | D206: S1 Pro | E206: Performance | F206: Delhi | G206: Dealer | H206: EMI | I206: Red | J206: SP-006 | K206: 3 | L206: 137776 | M206: 0.048 | N206: 413328 | O206: 19839.74 | P206: 393488.26 | Q206: 5 | R206: 210 | S206: 4.1 | T206: 13 | U206: 5
A207: EV10206 | B207: 45845 | C207: Vida | D207: V2 | E207: Premium | F207: Delhi | G207: Online | H207: Finance | I207: Blue | J207: SP-002 | K207: 2 | L207: 104333 | M207: 0.089 | N207: 208666 | O207: 18571.27 | P207: 190094.73 | Q207: 4 | R207: 181 | S207: 4.4 | T207: 10 | U207: 5
A208: EV10207 | B208: 45718 | C208: Revolt | D208: RV1 | E208: Premium | F208: Bengaluru | G208: Online | H208: Finance | I208: Grey | J208: SP-008 | K208: 5 | L208: 128966 | M208: 0.082 | N208: 644830 | O208: 52876.06 | P208: 591953.94 | Q208: 5 | R208: 203 | S208: 4.8 | T208: 14 | U208: 5
A209: EV10208 | B209: 45892 | C209: Bajaj | D209: Chetak Premium | E209: Performance | F209: Kochi | G209: Online | H209: EMI | I209: Red | J209: SP-011 | K209: 2 | L209: 143876 | M209: 0.119 | N209: 287752 | O209: 34242.49 | P209: 253509.51 | Q209: 4 | R209: 201 | S209: 3.6 | T209: 10 | U209: 5
A210: EV10209 | B210: 45931 | C210: Hero Electric | D210: Optima | E210: Premium | F210: Delhi | G210: Corporate | H210: EMI | I210: Grey | J210: SP-016 | K210: 2 | L210: 99774 | M210: 0.082 | N210: 199548 | O210: 16362.94 | P210: 183185.06 | Q210: 5 | R210: 206 | S210: 3.8 | T210: 12 | U210: 2
A211: EV10210 | B211: 45904 | C211: Ola Electric | D211: S1 Air | E211: Premium | F211: Pune | G211: Dealer | H211: Finance | I211: Red | J211: SP-009 | K211: 1 | L211: 121852 | M211: 0.097 | N211: 121852 | O211: 11819.64 | P211: 110032.36 | Q211: 3 | R211: 161 | S211: 3.4 | T211: 2 | U211: 5
A212: EV10211 | B212: 45693 | C212: Hero Electric | D212: Photon | E212: Performance | F212: Pune | G212: Dealer | H212: EMI | I212: Black | J212: SP-029 | K212: 1 | L212: 123011 | M212: 0.043 | N212: 123011 | O212: 5289.47 | P212: 117721.53 | Q212: 4 | R212: 173 | S212: 3.6 | T212: 3 | U212: 5
A213: EV10212 | B213: 45798 | C213: TVS | D213: X | E213: Performance | F213: Delhi | G213: Corporate | H213: Cash | I213: Green | J213: SP-003 | K213: 1 | L213: 191914 | M213: 0.035 | N213: 191914 | O213: 6716.99 | P213: 185197.01 | Q213: 5 | R213: 199 | S213: 4.4 | T213: 10 | U213: 2
A214: EV10213 | B214: 46016 | C214: TVS | D214: iQube | E214: Premium | F214: Delhi | G214: Online | H214: Finance | I214: Grey | J214: SP-020 | K214: 2 | L214: 123749 | M214: 0.099 | N214: 247498 | O214: 24502.3 | P214: 222995.7 | Q214: 3 | R214: 140 | S214: 4.5 | T214: 5 | U214: 2
... A225: EV10224 | B225: 45993 | C225: Hero Electric | D225: Optima | E225: Performance | F225: Hyderabad | G225: Fleet | H225: EMI | I225: White | J225: SP-024 | K225: 4 | L225: 101335 | M225: 0.1 | N225: 405340 | O225: 40534 | P225: 364806 | Q225: 4 | R225: 170 | S225: 4 | T225: 11 | U225: 2
A226: EV10225 | B226: 45970 | C226: Ampere | D226: Magnus EX | E226: Commuter | G226: Online | H226: Cash | I226: Grey | J226: SP-025 | K226: 3 | L226: 107257 | M226: 0.082 | N226: 321771 | O226: 26385.22 | P226: 295385.78 | Q226: 4 | R226: 182 | S226: 3.8 | T226: 6 | U226: 5
A227: EV10226 | B227: 45726 | C227: Bajaj | D227: Chetak Urbane | E227: Performance | F227: Kolkata | G227: Fleet | H227: Cash | I227: Grey | J227: SP-020 | K227: 1 | L227: 125967 | M227: 0.049 | N227: 125967 | O227: 6172.38 | P227: 119794.62 | Q227: 3 | R227: 150 | S227: 4.7 | T227: 3 | U227: 3
A228: EV10227 | B228: 45736 | C228: Ampere | D228: Magnus EX | E228: Premium | F228: Pune | G228: Online | H228: Cash | I228: Red | J228: SP-030 | K228: 1 | L228: 115427 | M228: 0.099 | N228: 115427 | O228: 11427.27 | P228: 103999.73 | Q228: 4 | R228: 181 | S228: 4 | T228: 11 | U228: 2
A229: EV10228 | B229: 45739 | C229: Ather | D229: 450X | E229: Premium | F229: Ahmedabad | G229: Online | H229: Finance | I229: Green | J229: SP-026 | K229: 2 | L229: 144881 | M229: 0.055 | N229: 289762 | O229: 15936.91 | P229: 273825.09 | Q229: 3 | R229: 154 | S229: 3.8 | T229: 10 | U229: 5
A230: EV10229 | B230: 45952 | C230: TVS | D230: iQube | E230: Premium | F230: Chennai | G230: Online | H230: Finance | I230: Blue | J230: SP-006 | K230: 1 | L230: 133696 | M230: 0.027 | N230: 133696 | O230: 3609.79 | P230: 130086.21 | Q230: 3 | R230: 159 | S230: 4.9 | T230: 4 | U230: 5
A231: EV10230 | B231: 45923 | C231: Revolt | D231: RV400 | E231: Performance | F231: Chennai | G231: Corporate | H231: Finance | I231: Red | J231: SP-002 | K231: 1 | L231: 144772 | M231: 0.078 | N231: 144772 | O231: 11292.22 | P231: 133479.78 | Q231: 4 | R231: 207 | S231: 3.7 | T231: 12 | U231: 3
A232: EV10231 | B232: 45941 | C232: Ampere | D232: Magnus EX | E232: Commuter | F232: Kochi | G232: Online | H232: EMI | I232: Green | J232: SP-018 | K232: 2 | L232: 109338 | M232: 0.114 | N232: 218676 | O232: 24929.06 | P232: 193746.94 | Q232: 4 | R232: 191 | S232: 4.8 | T232: 7 | U232: 3
...

Sheet Cleaned Data
A1: Order_ID | B1: Order_Date | C1: Brand | D1: Model | E1: Segment | F1: City | G1: Sales_Channel | H1: Payment_Method | I1: Payment M | J1: Color | K1: Salesperson_ID | L1: Units_Sold | M1: Unit_Price | N1: Discount_Pct | O1: Cleaned Dis% | P1: Gross_Sales | Q1: Discount_Amount | R1: Net_Sales | S1: Battery_kWh | T1: Range_km | U1: Customer_Rating | V1: Delivery_Days | W1: Cleaned Delivery Days | X1: Warranty_Years | Y1: ASP | Z1: Month-Year | AA1: Month | AB1: Quarter
A2: EV10001 | B2: 46006 | C2: Revolt | D2: RV1 | E2: Premium | F2: Chennai | G2: Online | H2: Finance | I2: =IF('Cleaned Data'!H2="Emi","EMI",'Cleaned Data'!H2) -> Finance | J2: Green | K2: SP-002 | L2: 1 | M2: 125898 | N2: 0.08 | O2: =IF(TRIM(N2&"")="","missing",N2) -> 0.08 | P2: 125898 | Q2: 10071.84 | R2: 115826.16 | S2: 3 | T2: 162 | U2: 3.7 | V2: 6 | W2: =IF('Cleaned Data'!V2<0,"Review",'Cleaned Data'!V2) -> 6 | X2: 5 | Y2: =IFERROR('Cleaned Data'!R2/'Cleaned Data'!L2,0) -> 115826.16 | Z2: =TEXT(EV_Sales[[#This Row],[Order_Date]],"mmm-yyyy") -> Dec-2025 | AA2: =MONTH(EV_Sales[[#This Row],[Order_Date]]) -> 12 | AB2: ="Q"&ROUNDUP(MONTH(EV_Sales[[#This Row],[Order_Date]])/3,0) -> Q4
A3: EV10002 | B3: 45934 | C3: Vida | D3: V2 | E3: Premium | F3: Bengaluru | G3: Fleet | H3: Emi | I3: =IF('Cleaned Data'!H3="Emi","EMI",'Cleaned Data'!H3) -> EMI | J3: Red | K3: SP-025 | L3: 2 | M3: 112819 | N3: 0.021 | O3: =IF(TRIM(N3&"")="","missing",N3) -> 0.021 | P3: 225638 | Q3: 4738.4 | R3: 220899.6 | S3: 2 | T3: 116 | U3: 4.4 | V3: 13 | W3: =IF('Cleaned Data'!V3<0,"Review",'Cleaned Data'!V3) -> 13 | X3: 5 | Y3: =IFERROR('Cleaned Data'!R3/'Cleaned Data'!L3,0) -> 110449.8 | Z3: =TEXT(EV_Sales[[#This Row],[Order_Date]],"mmm-yyyy") -> Oct-2025 | AA3: =MONTH(EV_Sales[[#This Row],[Order_Date]]) -> 10 | AB3: ="Q"&ROUNDUP(MONTH(EV_Sales[[#This Row],[Order_Date]])/3,0) -> Q4
A4: EV10003 | B4: 45964 | C4: TVS | D4: iQube | E4: Premium | F4: Hyderabad | G4: Fleet | H4: Emi | I4: =IF('Cleaned Data'!H4="Emi","EMI",'Cleaned Data'!H4) -> EMI | J4: Red | K4: SP-007 | L4: 2 | M4: 125383 | N4: 0.021 | O4: =IF(TRIM(N4&"")="","missing",N4) -> 0.021 | P4: 250766 | Q4: 5266.09 | R4: 245499.91 | S4: 5 | T4: 175 | U4: 4.6 | V4: 11 | W4: =IF('Cleaned Data'!V4<0,"Review",'Cleaned Data'!V4) -> 11 | X4: 2 | Y4: =IFERROR('Cleaned Data'!R4/'Cleaned Data'!L4,0) -> 122749.96 | Z4: =TEXT(EV_Sales[[#This Row],[Order_Date]],"mmm-yyyy") -> Nov-2025 | AA4: =MONTH(EV_Sales[[#This Row],[Order_Date]]) -> 11 | AB4: ="Q"&ROUNDUP(MONTH(EV_Sales[[#This Row],[Order_Date]])/3,0) -> Q4
A5: EV10004 | B5: 45921 | C5: Bajaj | D5: Chetak Premium | E5: Commuter | F5: Mumbai | G5: Online | H5: Finance | I5: =IF('Cleaned Data'!H5="Emi","EMI",'Cleaned Data'!H5) -> Finance | J5: White | K5: SP-030 | L5: 1 | M5: 160095 | N5: 0.046 | O5: =IF(TRIM(N5&"")="","missing",N5) -> 0.046 | P5: 160095 | Q5: 7364.37 | R5: 152730.63 | S5: 4 | T5: 184 | U5: 3.2 | V5: 11 | W5: =IF('Cleaned Data'!V5<0,"Review",'Cleaned Data'!V5) -> 11 | X5: 3 | Y5: =IFERROR('Cleaned Data'!R5/'Cleaned Data'!L5,0) -> 152730.63 | Z5: =TEXT(EV_Sales[[#This Row],[Order_Date]],"mmm-yyyy") -> Sep-2025 | AA5: =MONTH(EV_Sales[[#This Row],[Order_Date]]) -> 9 | AB5: ="Q"&ROUNDUP(MONTH(EV_Sales[[#This Row],[Order_Date]])/3,0) -> Q3
A6: EV10005 | B6: 46008 | C6: Bajaj | D6: Chetak Urbane | E6: Commuter | F6: Ahmedabad | G6: Online | H6: Cash | I6: =IF('Cleaned Data'!H6="Emi","EMI",'Cleaned Data'!H6) -> Cash | J6: Red | K6: SP-028 | L6: 4 | M6: 114286 | N6: 0.04 | O6: =IF(TRIM(N6&"")="","missing",N6) -> 0.04 | P6: 457144 | Q6: 18285.76 | R6: 438858.24 | S6: 2 | T6: 133 | U6: 3.4 | V6: 3 | W6: =IF('Cleaned Data'!V6<0,"Review",'Cleaned Data'!V6) -> 3 | X6: 5 | Y6: =IFERROR('Cleaned Data'!R6/'Cleaned Data'!L6,0) -> 109714.56 | Z6: =TEXT(EV_Sales[[#This Row],[Order_Date]],"mmm-yyyy") -> Dec-2025 | AA6: =MONTH(EV_Sales[[#This Row],[Order_Date]]) -> 12 | AB6: ="Q"&ROUNDUP(MONTH(EV_Sales[[#This Row],[Order_Date]])/3,0) -> Q4
A7: EV10006 | B7: 45698 | C7: Bajaj | D7: Chetak Premium | E7: Commuter | F7: Ahmedabad | G7: Corporate | H7: Emi | I7: =IF('Cleaned Data'!H7="Emi","EMI",'Cleaned Data'!H7) -> EMI | J7: Black | K7: SP-027 | L7: 1 | M7: 144470 | N7: 0.022 | O7: =IF(TRIM(N7&"")="","missing",N7) -> 0.022 | P7: 144470 | Q7: 3178.34 | R7: 141291.66 | S7: 3 | T7: 145 | U7: 3.7 | V7: 12 | W7: =IF('Cleaned Data'!V7<0,"Review",'Cleaned Data'!V7) -> 12 | X7: 5 | Y7: =IFERROR('Cleaned Data'!R7/'Cleaned Data'!L7,0) -> 141291.66 | Z7: =TEXT(EV_Sales[[#This Row],[Order_Date]],"mmm-yyyy") -> Feb-2025 | AA7: =MONTH(EV_Sales[[#This Row],[Order_Date]]) -> 2 | AB7: ="Q"&ROUNDUP(MONTH(EV_Sales[[#This Row],[Order_Date]])/3,0) -> Q1
A8: EV10007 | B8: 45888 | C8: Hero Electric | D8: Photon | E8: Performance | F8: Ahmedabad | G8: Online | H8: Emi | I8: =IF('Cleaned Data'!H8="Emi","EMI",'Cleaned Data'!H8) -> EMI | J8: Blue | K8: SP-001 | L8: 2 | M8: 122830 | N8: 0.105 | O8: =IF(TRIM(N8&"")="","missing",N8) -> 0.105 | P8: 245660 | Q8: 25794.3 | R8: 219865.7 | S8: 3 | T8: 161 | U8: 3.8 | V8: 9 | W8: =IF('Cleaned Data'!V8<0,"Review",'Cleaned Data'!V8) -> 9 | X8: 2 | Y8: =IFERROR('Cleaned Data'!R8/'Cleaned Data'!L8,0) -> 109932.85 | Z8: =TEXT(EV_Sales[[#This Row],[Order_Date]],"mmm-yyyy") -> Aug-2025 | AA8: =MONTH(EV_Sales[[#This Row],[Order_Date]]) -> 8 | AB8: ="Q"&ROUNDUP(MONTH(EV_Sales[[#This Row],[Order_Date]])/3,0) -> Q3
A9: EV10008 | B9: 45788 | C9: TVS | D9: iQube | E9: Performance | F9: Kolkata | G9: Dealer | H9: Cash | I9: =IF('Cleaned Data'!H9="Emi","EMI",'Cleaned Data'!H9) -> Cash | J9: Red | K9: SP-030 | L9: 3 | M9: 127322 | N9: 0.097 | O9: =IF(TRIM(N9&"")="","missing",N9) -> 0.097 | P9: 381966 | Q9: 37050.7 | R9: 344915.3 | S9: 3 | T9: 132 | U9: 4.5 | V9: 11 | W9: =IF('Cleaned Data'!V9<0,"Review",'Cleaned Data'!V9) -> 11 | X9: 2 | Y9: =IFERROR('Cleaned Data'!R9/'Cleaned Data'!L9,0) -> 114971.77 | Z9: =TEXT(EV_Sales[[#This Row],[Order_Date]],"mmm-yyyy") -> May-2025 | AA9: =MONTH(EV_Sales[[#This Row],[Order_Date]]) -> 5 | AB9: ="Q"&ROUNDUP(MONTH(EV_Sales[[#This Row],[Order_Date]])/3,0) -> Q2
A10: EV10009 | B10: 45888 | C10: Hero Electric | D10: Optima | E10: Commuter | F10: Jaipur | G10: Dealer | H10: Finance | I10: =IF('Cleaned Data'!H10="Emi","EMI",'Cleaned Data'!H10) -> Finance | J10: Red | K10: SP-028 | L10: 1 | M10: 109806 | N10: 0.043 | O10: =IF(TRIM(N10&"")="","missing",N10) -> 0.043 | P10: 109806 | Q10: 4721.66 | R10: 105084.34 | S10: 2 | T10: 136 | U10: 3.9 | V10: 3 | W10: =IF('Cleaned Data'!V10<0,"Review",'Cleaned Data'!V10) -> 3 | X10: 3 | Y10: =IFERROR('Cleaned Data'!R10/'Cleaned Data'!L10,0) -> 105084.34 | Z10: =TEXT(EV_Sales[[#This Row],[Order_Date]],"mmm-yyyy") -> Aug-2025 | AA10: =MONTH(EV_Sales[[#This Row],[Order_Date]]) -> 8 | AB10: ="Q"&ROUNDUP(MONTH(EV_Sales[[#This Row],[Order_Date]])/3,0) -> Q3
A11: EV10010 | B11: 45997 | C11: Bajaj | D11: Chetak Urbane | E11: Premium | F11: Jaipur | G11: Fleet | H11: Cash | I11: =IF('Cleaned Data'!H11="Emi","EMI",'Cleaned Data'!H11) -> Cash | J11: Black | K11: SP-003 | L11: 4 | M11: 121860 | N11: 0.101 | O11: =IF(TRIM(N11&"")="","missing",N11) -> 0.101 | P11: 487440 | Q11: 49231.44 | R11: 438208.56 | S11: 5 | T11: 191 | U11: 4 | V11: 10 | W11: =IF('Cleaned Data'!V11<0,"Review",'Cleaned Data'!V11) -> 10 | X11: 5 | Y11: =IFERROR('Cleaned Data'!R11/'Cleaned Data'!L11,0) -> 109552.14 | Z11: =TEXT(EV_Sales[[#This Row],[Order_Date]],"mmm-yyyy") -> Dec-2025 | AA11: =MONTH(EV_Sales[[#This Row],[Order_Date]]) -> 12 | AB11: ="Q"&ROUNDUP(MONTH(EV_Sales[[#This Row],[Order_Date]])/3,0) -> Q4
A12: EV10011 | B12: 45794 | C12: Revolt | D12: RV1 | E12: Commuter | F12: Delhi | G12: Online | H12: Finance | I12: =IF('Cleaned Data'!H12="Emi","EMI",'Cleaned Data'!H12) -> Finance | J12: White | K12: SP-003 | L12: 1 | M12: 124432 | N12: 0.047 | O12: =IF(TRIM(N12&"")="","missing",N12) -> 0.047 | P12: 124432 | Q12: 5848.3 | R12: 118583.7 | S12: 3 | T12: 158 | U12: 3.8 | V12: 9 | W12: =IF('Cleaned Data'!V12<0,"Review",'Cleaned Data'!V12) -> 9 | X12: 2 | Y12: =IFERROR('Cleaned Data'!R12/'Cleaned Data'!L12,0) -> 118583.7 | Z12: =TEXT(EV_Sales[[#This Row],[Order_Date]],"mmm-yyyy") -> May-2025 | AA12: =MONTH(EV_Sales[[#This Row],[Order_Date]]) -> 5 | AB12: ="Q"&ROUNDUP(MONTH(EV_Sales[[#This Row],[Order_Date]])/3,0) -> Q2
A13: EV10012 | B13: 45770 | C13: Ather | D13: 450X | E13: Premium | F13: Mumbai | G13: Dealer | H13: Finance | I13: =IF('Cleaned Data'!H13="Emi","EMI",'Cleaned Data'!H13) -> Finance | J13: Green | K13: SP-023 | L13: 5 | M13: 141715 | N13: 0.118 | O13: =IF(TRIM(N13&"")="","missing",N13) -> 0.118 | P13: 708575 | Q13: 83611.85 | R13: 624963.15 | S13: 3 | T13: 163 | U13: 4 | V13: 2 | W13: =IF('Cleaned Data'!V13<0,"Review",'Cleaned Data'!V13) -> 2 | X13: 5 | Y13: =IFERROR('Cleaned Data'!R13/'Cleaned Data'!L13,0) -> 124992.63 | Z13: =TEXT(EV_Sales[[#This Row],[Order_Date]],"mmm-yyyy") -> Apr-2025 | AA13: =MONTH(EV_Sales[[#This Row],[Order_Date]]) -> 4 | AB13: ="Q"&ROUNDUP(MONTH(EV_Sales[[#This Row],[Order_Date]])/3,0) -> Q2
... A23: EV10022 | B23: 45921 | C23: Bajaj | D23: Chetak Premium | E23: Premium | F23: Bengaluru | G23: Dealer | H23: Finance | I23: =IF('Cleaned Data'!H23="Emi","EMI",'Cleaned Data'!H23) -> Finance | J23: Green | K23: SP-029 | L23: 2 | M23: 157711 | N23: 0.109 | O23: =IF(TRIM(N23&"")="","missing",N23) -> 0.109 | P23: 315422 | Q23: 34381 | R23: 281041 | S23: 3 | T23: 154 | U23: 4 | V23: 8 | W23: =IF('Cleaned Data'!V23<0,"Review",'Cleaned Data'!V23) -> 8 | X23: 5 | Y23: =IFERROR('Cleaned Data'!R23/'Cleaned Data'!L23,0) -> 140520.5 | Z23: =TEXT(EV_Sales[[#This Row],[Order_Date]],"mmm-yyyy") -> Sep-2025 | AA23: =MONTH(EV_Sales[[#This Row],[Order_Date]]) -> 9 | AB23: ="Q"&ROUNDUP(MONTH(EV_Sales[[#This Row],[Order_Date]])/3,0) -> Q3
A24: EV10023 | B24: 45715 | C24: Ampere | D24: Primus | E24: Performance | F24: Hyderabad | G24: Online | H24: Cash | I24: =IF('Cleaned Data'!H24="Emi","EMI",'Cleaned Data'!H24) -> Cash | J24: Red | K24: SP-030 | L24: 1 | M24: 141784 | N24: 0.102 | O24: =IF(TRIM(N24&"")="","missing",N24) -> 0.102 | P24: 141784 | Q24: 14461.97 | R24: 127322.03 | S24: 3 | T24: 164 | U24: Missing | V24: 6 | W24: =IF('Cleaned Data'!V24<0,"Review",'Cleaned Data'!V24) -> 6 | X24: 2 | Y24: =IFERROR('Cleaned Data'!R24/'Cleaned Data'!L24,0) -> 127322.03 | Z24: =TEXT(EV_Sales[[#This Row],[Order_Date]],"mmm-yyyy") -> Feb-2025 | AA24: =MONTH(EV_Sales[[#This Row],[Order_Date]]) -> 2 | AB24: ="Q"&ROUNDUP(MONTH(EV_Sales[[#This Row],[Order_Date]])/3,0) -> Q1
A25: EV10024 | B25: 45968 | C25: Revolt | D25: RV400 | E25: Performance | F25: Kochi | G25: Dealer | H25: Finance | I25: =IF('Cleaned Data'!H25="Emi","EMI",'Cleaned Data'!H25) -> Finance | J25: Grey | K25: SP-030 | L25: 1 | M25: 134201 | N25: 0.117 | O25: =IF(TRIM(N25&"")="","missing",N25) -> 0.117 | P25: 134201 | Q25: 15701.52 | R25: 118499.48 | S25: 4 | T25: 180 | U25: 3.9 | V25: 4 | W25: =IF('Cleaned Data'!V25<0,"Review",'Cleaned Data'!V25) -> 4 | X25: 3 | Y25: =IFERROR('Cleaned Data'!R25/'Cleaned Data'!L25,0) -> 118499.48 | Z25: =TEXT(EV_Sales[[#This Row],[Order_Date]],"mmm-yyyy") -> Nov-2025 | AA25: =MONTH(EV_Sales[[#This Row],[Order_Date]]) -> 11 | AB25: ="Q"&ROUNDUP(MONTH(EV_Sales[[#This Row],[Order_Date]])/3,0) -> Q4
A26: EV10025 | B26: 45786 | C26: Revolt | D26: RV400 | E26: Commuter | F26: Kolkata | G26: Fleet | H26: Emi | I26: =IF('Cleaned Data'!H26="Emi","EMI",'Cleaned Data'!H26) -> EMI | J26: Grey | K26: SP-022 | L26: 1 | M26: 134666 | N26: 0.045 | O26: =IF(TRIM(N26&"")="","missing",N26) -> 0.045 | P26: 134666 | Q26: 6059.97 | R26: 128606.03 | S26: 4 | T26: 193 | U26: 4.7 | V26: 6 | W26: =IF('Cleaned Data'!V26<0,"Review",'Cleaned Data'!V26) -> 6 | X26: 2 | Y26: =IFERROR('Cleaned Data'!R26/'Cleaned Data'!L26,0) -> 128606.03 | Z26: =TEXT(EV_Sales[[#This Row],[Order_Date]],"mmm-yyyy") -> May-2025 | AA26: =MONTH(EV_Sales[[#This Row],[Order_Date]]) -> 5 | AB26: ="Q"&ROUNDUP(MONTH(EV_Sales[[#This Row],[Order_Date]])/3,0) -> Q2
A27: EV10026 | B27: 45733 | C27: Hero Electric | D27: Optima | E27: Premium | F27: Chennai | G27: Corporate | H27: Finance | I27: =IF('Cleaned Data'!H27="Emi","EMI",'Cleaned Data'!H27) -> Finance | J27: White | K27: SP-022 | L27: 2 | M27: 101032 | N27: 0.032 | O27: =IF(TRIM(N27&"")="","missing",N27) -> 0.032 | P27: 202064 | Q27: 6466.05 | R27: 195597.95 | S27: 3 | T27: 172 | U27: 4.4 | V27: 5 | W27: =IF('Cleaned Data'!V27<0,"Review",'Cleaned Data'!V27) -> 5 | X27: 2 | Y27: =IFERROR('Cleaned Data'!R27/'Cleaned Data'!L27,0) -> 97798.975 | Z27: =TEXT(EV_Sales[[#This Row],[Order_Date]],"mmm-yyyy") -> Mar-2025 | AA27: =MONTH(EV_Sales[[#This Row],[Order_Date]]) -> 3 | AB27: ="Q"&ROUNDUP(MONTH(EV_Sales[[#This Row],[Order_Date]])/3,0) -> Q1
A28: EV10027 | B28: 45947 | C28: Hero Electric | D28: Photon | E28: Premium | F28: Delhi | G28: Fleet | H28: Emi | I28: =IF('Cleaned Data'!H28="Emi","EMI",'Cleaned Data'!H28) -> EMI | J28: Red | K28: SP-024 | L28: 1 | M28: 108346 | N28: 0.113 | O28: =IF(TRIM(N28&"")="","missing",N28) -> 0.113 | P28: 108346 | Q28: 12243.1 | R28: 96102.9 | S28: 4 | T28: 205 | U28: 4.3 | V28: 9 | W28: =IF('Cleaned Data'!V28<0,"Review",'Cleaned Data'!V28) -> 9 | X28: 5 | Y28: =IFERROR('Cleaned Data'!R28/'Cleaned Data'!L28,0) -> 96102.9 | Z28: =TEXT(EV_Sales[[#This Row],[Order_Date]],"mmm-yyyy") -> Oct-2025 | AA28: =MONTH(EV_Sales[[#This Row],[Order_Date]]) -> 10 | AB28: ="Q"&ROUNDUP(MONTH(EV_Sales[[#This Row],[Order_Date]])/3,0) -> Q4
A29: EV10028 | B29: 45820 | C29: Bajaj | D29: Chetak Urbane | E29: Commuter | F29: Mumbai | G29: Dealer | H29: Emi | I29: =IF('Cleaned Data'!H29="Emi","EMI",'Cleaned Data'!H29) -> EMI | J29: White | K29: SP-003 | L29: 2 | M29: 120498 | N29: 0.075 | O29: =IF(TRIM(N29&"")="","missing",N29) -> 0.075 | P29: 240996 | Q29: 18074.7 | R29: 222921.3 | S29: 5 | T29: 205 | U29: 4.1 | V29: 11 | W29: =IF('Cleaned Data'!V29<0,"Review",'Cleaned Data'!V29) -> 11 | X29: 5 | Y29: =IFERROR('Cleaned Data'!R29/'Cleaned Data'!L29,0) -> 111460.65 | Z29: =TEXT(EV_Sales[[#This Row],[Order_Date]],"mmm-yyyy") -> Jun-2025 | AA29: =MONTH(EV_Sales[[#This Row],[Order_Date]]) -> 6 | AB29: ="Q"&ROUNDUP(MONTH(EV_Sales[[#This Row],[Order_Date]])/3,0) -> Q2
A30: EV10029 | B30: 45747 | C30: Revolt | D30: RV400 | E30: Commuter | F30: Ahmedabad | G30: Fleet | H30: Cash | I30: =IF('Cleaned Data'!H30="Emi","EMI",'Cleaned Data'!H30) -> Cash | J30: Grey | K30: SP-029 | L30: 1 | M30: 148159 | N30: 0.022 | O30: =IF(TRIM(N30&"")="","missing",N30) -> 0.022 | P30: 148159 | Q30: 3259.5 | R30: 144899.5 | S30: 4 | T30: 174 | U30: 3.9 | V30: 6 | W30: =IF('Cleaned Data'!V30<0,"Review",'Cleaned Data'!V30) -> 6 | X30: 3 | Y30: =IFERROR('Cleaned Data'!R30/'Cleaned Data'!L30,0) -> 144899.5 | Z30: =TEXT(EV_Sales[[#This Row],[Order_Date]],"mmm-yyyy") -> Mar-2025 | AA30: =MONTH(EV_Sales[[#This Row],[Order_Date]]) -> 3 | AB30: ="Q"&ROUNDUP(MONTH(EV_Sales[[#This Row],[Order_Date]])/3,0) -> Q1
A31: EV10030 | B31: 46014 | C31: Ather | D31: 450S | E31: Premium | F31: Chennai | G31: Fleet | H31: Cash | I31: =IF('Cleaned Data'!H31="Emi","EMI",'Cleaned Data'!H31) -> Cash | J31: Grey | K31: SP-023 | L31: 3 | M31: 136884 | N31: 0.119 | O31: =IF(TRIM(N31&"")="","missing",N31) -> 0.119 | P31: 410652 | Q31: 48867.59 | R31: 361784.41 | S31: 3 | T31: 179 | U31: 3.8 | V31: 9 | W31: =IF('Cleaned Data'!V31<0,"Review",'Cleaned Data'!V31) -> 9 | X31: 5 | Y31: =IFERROR('Cleaned Data'!R31/'Cleaned Data'!L31,0) -> 120594.8 | Z31: =TEXT(EV_Sales[[#This Row],[Order_Date]],"mmm-yyyy") -> Dec-2025 | AA31: =MONTH(EV_Sales[[#This Row],[Order_Date]]) -> 12 | AB31: ="Q"&ROUNDUP(MONTH(EV_Sales[[#This Row],[Order_Date]])/3,0) -> Q4
A32: EV10031 | B32: 46018 | C32: Ather | D32: Rizta | E32: Commuter | F32: Bengaluru | G32: Fleet | H32: Cash | I32: =IF('Cleaned Data'!H32="Emi","EMI",'Cleaned Data'!H32) -> Cash | J32: Red | K32: SP-014 | L32: 1 | M32: 136998 | N32: 0.07 | O32: =IF(TRIM(N32&"")="","missing",N32) -> 0.07 | P32: 136998 | Q32: 9589.86 | R32: 127408.14 | S32: 3 | T32: 156 | U32: 4 | V32: 5 | W32: =IF('Cleaned Data'!V32<0,"Review",'Cleaned Data'!V32) -> 5 | X32: 2 | Y32: =IFERROR('Cleaned Data'!R32/'Cleaned Data'!L32,0) -> 127408.14 | Z32: =TEXT(EV_Sales[[#This Row],[Order_Date]],"mmm-yyyy") -> Dec-2025 | AA32: =MONTH(EV_Sales[[#This Row],[Order_Date]]) -> 12 | AB32: ="Q"&ROUNDUP(MONTH(EV_Sales[[#This Row],[Order_Date]])/3,0) -> Q4
A33: EV10032 | B33: 45709 | C33: Revolt | D33: RV1 | E33: Performance | F33: Jaipur | G33: Corporate | H33: Cash | I33: =IF('Cleaned Data'!H33="Emi","EMI",'Cleaned Data'!H33) -> Cash | J33: Grey | K33: SP-010 | L33: 2 | M33: 123414 | N33: 0.065 | O33: =IF(TRIM(N33&"")="","missing",N33) -> 0.065 | P33: 246828 | Q33: 16043.82 | R33: 230784.18 | S33: 3 | T33: 178 | U33: 3.6 | V33: 5 | W33: =IF('Cleaned Data'!V33<0,"Review",'Cleaned Data'!V33) -> 5 | X33: 2 | Y33: =IFERROR('Cleaned Data'!R33/'Cleaned Data'!L33,0) -> 115392.09 | Z33: =TEXT(EV_Sales[[#This Row],[Order_Date]],"mmm-yyyy") -> Feb-2025 | AA33: =MONTH(EV_Sales[[#This Row],[Order_Date]]) -> 2 | AB33: ="Q"&ROUNDUP(MONTH(EV_Sales[[#This Row],[Order_Date]])/3,0) -> Q1
A34: EV10033 | B34: 45880 | C34: Ola Electric | D34: S1 X | E34: Premium | F34: Ahmedabad | G34: Online | H34: Cash | I34: =IF('Cleaned Data'!H34="Emi","EMI",'Cleaned Data'!H34) -> Cash | J34: White | K34: SP-027 | L34: 1 | M34: 109534 | N34: 0.075 | O34: =IF(TRIM(N34&"")="","missing",N34) -> 0.075 | P34: 109534 | Q34: 8215.05 | R34: 101318.95 | S34: 4 | T34: 183 | U34: 4.1 | V34: 7 | W34: =IF('Cleaned Data'!V34<0,"Review",'Cleaned Data'!V34) -> 7 | X34: 5 | Y34: =IFERROR('Cleaned Data'!R34/'Cleaned Data'!L34,0) -> 101318.95 | Z34: =TEXT(EV_Sales[[#This Row],[Order_Date]],"mmm-yyyy") -> Aug-2025 | AA34: =MONTH(EV_Sales[[#This Row],[Order_Date]]) -> 8 | AB34: ="Q"&ROUNDUP(MONTH(EV_Sales[[#This Row],[Order_Date]])/3,0) -> Q3
A35: EV10034 | B35: 45662 | C35: Ola Electric | D35: S1 Air | E35: Commuter | F35: Hyderabad | G35: Fleet | H35: Finance | I35: =IF('Cleaned Data'!H35="Emi","EMI",'Cleaned Data'!H35) -> Finance | J35: Red | K35: SP-019 | L35: 2 | M35: 111854 | N35: 0.078 | O35: =IF(TRIM(N35&"")="","missing",N35) -> 0.078 | P35: 223708 | Q35: 17449.22 | R35: 206258.78 | S35: 5 | T35: 196 | U35: 4.3 | V35: 8 | W35: =IF('Cleaned Data'!V35<0,"Review",'Cleaned Data'!V35) -> 8 | X35: 2 | Y35: =IFERROR('Cleaned Data'!R35/'Cleaned Data'!L35,0) -> 103129.39 | Z35: =TEXT(EV_Sales[[#This Row],[Order_Date]],"mmm-yyyy") -> Jan-2025 | AA35: =MONTH(EV_Sales[[#This Row],[Order_Date]]) -> 1 | AB35: ="Q"&ROUNDUP(MONTH(EV_Sales[[#This Row],[Order_Date]])/3,0) -> Q1
A36: EV10035 | B36: 45839 | C36: Hero Electric | D36: Photon | E36: Performance | F36: Jaipur | G36: Corporate | H36: Cash | I36: =IF('Cleaned Data'!H36="Emi","EMI",'Cleaned Data'!H36) -> Cash | J36: Blue | K36: SP-013 | L36: 2 | M36: 112104 | N36: 0.053 | O36: =IF(TRIM(N36&"")="","missing",N36) -> 0.053 | P36: 224208 | Q36: 11883.02 | R36: 212324.98 | S36: 3 | T36: 157 | U36: 3.4 | V36: 11 | W36: =IF('Cleaned Data'!V36<0,"Review",'Cleaned Data'!V36) -> 11 | X36: 2 | Y36: =IFERROR('Cleaned Data'!R36/'Cleaned Data'!L36,0) -> 106162.49 | Z36: =TEXT(EV_Sales[[#This Row],[Order_Date]],"mmm-yyyy") -> Jul-2025 | AA36: =MONTH(EV_Sales[[#This Row],[Order_Date]]) -> 7 | AB36: ="Q"&ROUNDUP(MONTH(EV_Sales[[#This Row],[Order_Date]])/3,0) -> Q3
... A97: EV10096 | B97: 46001 | C97: Hero Electric | D97: Optima | E97: Commuter | F97: Jaipur | G97: Dealer | H97: Finance | I97: =IF('Cleaned Data'!H97="Emi","EMI",'Cleaned Data'!H97) -> Finance | J97: Black | K97: SP-008 | L97: 1 | M97: 113169 | N97: 0.035 | O97: =IF(TRIM(N97&"")="","missing",N97) -> 0.035 | P97: 113169 | Q97: 3960.92 | R97: 109208.08 | S97: 3 | T97: 152 | U97: 4.8 | V97: 7 | W97: =IF('Cleaned Data'!V97<0,"Review",'Cleaned Data'!V97) -> 7 | X97: 5 | Y97: =IFERROR('Cleaned Data'!R97/'Cleaned Data'!L97,0) -> 109208.08 | Z97: =TEXT(EV_Sales[[#This Row],[Order_Date]],"mmm-yyyy") -> Dec-2025 | AA97: =MONTH(EV_Sales[[#This Row],[Order_Date]]) -> 12 | AB97: ="Q"&ROUNDUP(MONTH(EV_Sales[[#This Row],[Order_Date]])/3,0) -> Q4
A98: EV10097 | B98: 45836 | C98: TVS | D98: X | E98: Premium | F98: Ahmedabad | G98: Fleet | H98: Finance | I98: =IF('Cleaned Data'!H98="Emi","EMI",'Cleaned Data'!H98) -> Finance | J98: Red | K98: SP-001 | L98: 1 | M98: 175299 | N98: 0.119 | O98: =IF(TRIM(N98&"")="","missing",N98) -> 0.119 | P98: 175299 | Q98: 20860.58 | R98: 154438.42 | S98: 3 | T98: 192 | U98: Missing | V98: 5 | W98: =IF('Cleaned Data'!V98<0,"Review",'Cleaned Data'!V98) -> 5 | X98: 2 | Y98: =IFERROR('Cleaned Data'!R98/'Cleaned Data'!L98,0) -> 154438.42 | Z98: =TEXT(EV_Sales[[#This Row],[Order_Date]],"mmm-yyyy") -> Jun-2025 | AA98: =MONTH(EV_Sales[[#This Row],[Order_Date]]) -> 6 | AB98: ="Q"&ROUNDUP(MONTH(EV_Sales[[#This Row],[Order_Date]])/3,0) -> Q2
A99: EV10098 | B99: 45946 | C99: ola electric | D99: S1 Pro | E99: Performance | F99: Delhi | G99: Fleet | H99: Emi | I99: =IF('Cleaned Data'!H99="Emi","EMI",'Cleaned Data'!H99) -> EMI | J99: Grey | K99: SP-003 | L99: 4 | M99: 133217 | N99: 0.102 | O99: =IF(TRIM(N99&"")="","missing",N99) -> 0.102 | P99: 532868 | Q99: 54352.54 | R99: 478515.46 | S99: 3 | T99: 171 | U99: 3.7 | V99: 3 | W99: =IF('Cleaned Data'!V99<0,"Review",'Cleaned Data'!V99) -> 3 | X99: 3 | Y99: =IFERROR('Cleaned Data'!R99/'Cleaned Data'!L99,0) -> 119628.87 | Z99: =TEXT(EV_Sales[[#This Row],[Order_Date]],"mmm-yyyy") -> Oct-2025 | AA99: =MONTH(EV_Sales[[#This Row],[Order_Date]]) -> 10 | AB99: ="Q"&ROUNDUP(MONTH(EV_Sales[[#This Row],[Order_Date]])/3,0) -> Q4
A100: EV10099 | B100: 45666 | C100: TVS | D100: X | E100: Performance | F100: Kolkata | G100: Corporate | H100: Finance | I100: =IF('Cleaned Data'!H100="Emi","EMI",'Cleaned Data'!H100) -> Finance | J100: White | K100: SP-022 | L100: 5 | M100: 170509 | N100: 0.074 | O100: =IF(TRIM(N100&"")="","missing",N100) -> 0.074 | P100: 852545 | Q100: 63088.33 | R100: 789456.67 | S100: 4 | T100: 186 | U100: 4.4 | V100: 5 | W100: =IF('Cleaned Data'!V100<0,"Review",'Cleaned Data'!V100) -> 5 | X100: 3 | Y100: =IFERROR('Cleaned Data'!R100/'Cleaned Data'!L100,0) -> 157891.33 | Z100: =TEXT(EV_Sales[[#This Row],[Order_Date]],"mmm-yyyy") -> Jan-2025 | AA100: =MONTH(EV_Sales[[#This Row],[Order_Date]]) -> 1 | AB100: ="Q"&ROUNDUP(MONTH(EV_Sales[[#This Row],[Order_Date]])/3,0) -> Q1
A101: EV10100 | B101: 45660 | C101: Ola Electric | D101: S1 X | E101: Performance | F101: Kochi | G101: Corporate | H101: Emi | I101: =IF('Cleaned Data'!H101="Emi","EMI",'Cleaned Data'!H101) -> EMI | J101: Green | K101: SP-004 | L101: 1 | M101: 101110 | N101: 0.064 | O101: =IF(TRIM(N101&"")="","missing",N101) -> 0.064 | P101: 101110 | Q101: 6471.04 | R101: 94638.96 | S101: 4 | T101: 202 | U101: 4.6 | V101: 10 | W101: =IF('Cleaned Data'!V101<0,"Review",'Cleaned Data'!V101) -> 10 | X101: 2 | Y101: =IFERROR('Cleaned Data'!R101/'Cleaned Data'!L101,0) -> 94638.96 | Z101: =TEXT(EV_Sales[[#This Row],[Order_Date]],"mmm-yyyy") -> Jan-2025 | AA101: =MONTH(EV_Sales[[#This Row],[Order_Date]]) -> 1 | AB101: ="Q"&ROUNDUP(MONTH(EV_Sales[[#This Row],[Order_Date]])/3,0) -> Q1
A102: EV10101 | B102: 45878 | C102: Hero Electric | D102: Photon | E102: Performance | F102: Bengaluru | G102: Fleet | H102: Finance | I102: =IF('Cleaned Data'!H102="Emi","EMI",'Cleaned Data'!H102) -> Finance | J102: Blue | K102: SP-003 | L102: 3 | M102: 118705 | N102: 0.07 | O102: =IF(TRIM(N102&"")="","missing",N102) -> 0.07 | P102: 356115 | Q102: 24928.05 | R102: 331186.95 | S102: 4 | T102: 170 | U102: 4.4 | V102: 9 | W102: =IF('Cleaned Data'!V102<0,"Review",'Cleaned Data'!V102) -> 9 | X102: 2 | Y102: =IFERROR('Cleaned Data'!R102/'Cleaned Data'!L102,0) -> 110395.65 | Z102: =TEXT(EV_Sales[[#This Row],[Order_Date]],"mmm-yyyy") -> Aug-2025 | AA102: =MONTH(EV_Sales[[#This Row],[Order_Date]]) -> 8 | AB102: ="Q"&ROUNDUP(MONTH(EV_Sales[[#This Row],[Order_Date]])/3,0) -> Q3
A103: EV10102 | B103: 45864 | C103: Hero Electric | D103: Optima | E103: Premium | F103: Delhi | G103: Corporate | H103: Cash | I103: =IF('Cleaned Data'!H103="Emi","EMI",'Cleaned Data'!H103) -> Cash | J103: Red | K103: SP-026 | L103: 1 | M103: 105500 | N103: 0.107 | O103: =IF(TRIM(N103&"")="","missing",N103) -> 0.107 | P103: 105500 | Q103: 11288.5 | R103: 94211.5 | S103: 4 | T103: 176 | U103: 4.8 | V103: 5 | W103: =IF('Cleaned Data'!V103<0,"Review",'Cleaned Data'!V103) -> 5 | X103: 3 | Y103: =IFERROR('Cleaned Data'!R103/'Cleaned Data'!L103,0) -> 94211.5 | Z103: =TEXT(EV_Sales[[#This Row],[Order_Date]],"mmm-yyyy") -> Jul-2025 | AA103: =MONTH(EV_Sales[[#This Row],[Order_Date]]) -> 7 | AB103: ="Q"&ROUNDUP(MONTH(EV_Sales[[#This Row],[Order_Date]])/3,0) -> Q3
A104: EV10103 | B104: 45885 | C104: Hero Electric | D104: Photon | E104: Commuter | F104: Mumbai | G104: Fleet | H104: Cash | I104: =IF('Cleaned Data'!H104="Emi","EMI",'Cleaned Data'!H104) -> Cash | J104: Black | K104: SP-003 | L104: 4 | M104: 122601 | N104: 0.062 | O104: =IF(TRIM(N104&"")="","missing",N104) -> 0.062 | P104: 490404 | Q104: 30405.05 | R104: 459998.95 | S104: 3 | T104: 173 | U104: 4.2 | V104: 13 | W104: =IF('Cleaned Data'!V104<0,"Review",'Cleaned Data'!V104) -> 13 | X104: 5 | Y104: =IFERROR('Cleaned Data'!R104/'Cleaned Data'!L104,0) -> 114999.74 | Z104: =TEXT(EV_Sales[[#This Row],[Order_Date]],"mmm-yyyy") -> Aug-2025 | AA104: =MONTH(EV_Sales[[#This Row],[Order_Date]]) -> 8 | AB104: ="Q"&ROUNDUP(MONTH(EV_Sales[[#This Row],[Order_Date]])/3,0) -> Q3
A105: EV10104 | B105: 45744 | C105: Ola Electric | D105: S1 Air | E105: Performance | F105: Ahmedabad | G105: Corporate | H105: Cash | I105: =IF('Cleaned Data'!H105="Emi","EMI",'Cleaned Data'!H105) -> Cash | J105: Red | K105: SP-002 | L105: 2 | M105: 114102 | N105: 0.071 | O105: =IF(TRIM(N105&"")="","missing",N105) -> 0.071 | P105: 228204 | Q105: 16202.48 | R105: 212001.52 | S105: 3 | T105: 162 | U105: 3.8 | V105: 7 | W105: =IF('Cleaned Data'!V105<0,"Review",'Cleaned Data'!V105) -> 7 | X105: 2 | Y105: =IFERROR('Cleaned Data'!R105/'Cleaned Data'!L105,0) -> 106000.76 | Z105: =TEXT(EV_Sales[[#This Row],[Order_Date]],"mmm-yyyy") -> Mar-2025 | AA105: =MONTH(EV_Sales[[#This Row],[Order_Date]]) -> 3 | AB105: ="Q"&ROUNDUP(MONTH(EV_Sales[[#This Row],[Order_Date]])/3,0) -> Q1
A106: EV10105 | B106: 45802 | C106: Revolt | D106: RV1 | E106: Performance | F106: Kochi | G106: Corporate | H106: Finance | I106: =IF('Cleaned Data'!H106="Emi","EMI",'Cleaned Data'!H106) -> Finance | J106: Green | K106: SP-016 | L106: 1 | M106: 129086 | N106: 0.046 | O106: =IF(TRIM(N106&"")="","missing",N106) -> 0.046 | P106: 129086 | Q106: 5937.96 | R106: 123148.04 | S106: 4 | T106: 195 | U106: 3.8 | V106: 9 | W106: =IF('Cleaned Data'!V106<0,"Review",'Cleaned Data'!V106) -> 9 | X106: 2 | Y106: =IFERROR('Cleaned Data'!R106/'Cleaned Data'!L106,0) -> 123148.04 | Z106: =TEXT(EV_Sales[[#This Row],[Order_Date]],"mmm-yyyy") -> May-2025 | AA106: =MONTH(EV_Sales[[#This Row],[Order_Date]]) -> 5 | AB106: ="Q"&ROUNDUP(MONTH(EV_Sales[[#This Row],[Order_Date]])/3,0) -> Q2
A107: EV10106 | B107: 45923 | C107: Ola Electric | D107: S1 Pro | E107: Performance | F107: Chennai | G107: Fleet | H107: Cash | I107: =IF('Cleaned Data'!H107="Emi","EMI",'Cleaned Data'!H107) -> Cash | J107: Black | K107: SP-017 | L107: 2 | M107: 134456 | N107: 0.065 | O107: =IF(TRIM(N107&"")="","missing",N107) -> 0.065 | P107: 268912 | Q107: 17479.28 | R107: 251432.72 | S107: 4 | T107: 166 | U107: 3.4 | V107: 12 | W107: =IF('Cleaned Data'!V107<0,"Review",'Cleaned Data'!V107) -> 12 | X107: 2 | Y107: =IFERROR('Cleaned Data'!R107/'Cleaned Data'!L107,0) -> 125716.36 | Z107: =TEXT(EV_Sales[[#This Row],[Order_Date]],"mmm-yyyy") -> Sep-2025 | AA107: =MONTH(EV_Sales[[#This Row],[Order_Date]]) -> 9 | AB107: ="Q"&ROUNDUP(MONTH(EV_Sales[[#This Row],[Order_Date]])/3,0) -> Q3
A108: EV10107 | B108: 45969 | C108: Vida | D108: V2 | E108: Commuter | F108: Delhi | G108: Corporate | H108: Emi | I108: =IF('Cleaned Data'!H108="Emi","EMI",'Cleaned Data'!H108) -> EMI | J108: Green | K108: SP-005 | L108: 2 | M108: 116771 | N108: 0.041 | O108: =IF(TRIM(N108&"")="","missing",N108) -> 0.041 | P108: 233542 | Q108: 9575.22 | R108: 223966.78 | S108: 2 | T108: 145 | U108: 4.1 | V108: 6 | W108: =IF('Cleaned Data'!V108<0,"Review",'Cleaned Data'!V108) -> 6 | X108: 3 | Y108: =IFERROR('Cleaned Data'!R108/'Cleaned Data'!L108,0) -> 111983.39 | Z108: =TEXT(EV_Sales[[#This Row],[Order_Date]],"mmm-yyyy") -> Nov-2025 | AA108: =MONTH(EV_Sales[[#This Row],[Order_Date]]) -> 11 | AB108: ="Q"&ROUNDUP(MONTH(EV_Sales[[#This Row],[Order_Date]])/3,0) -> Q4
A109: EV10108 | B109: 45982 | C109: Hero Electric | D109: Optima | E109: Premium | F109: Jaipur | G109: Corporate | H109: Emi | I109: =IF('Cleaned Data'!H109="Emi","EMI",'Cleaned Data'!H109) -> EMI | J109: Blue | K109: SP-018 | L109: 1 | M109: 107294 | N109: 0.089 | O109: =IF(TRIM(N109&"")="","missing",N109) -> 0.089 | P109: 107294 | Q109: 9549.17 | R109: 97744.83 | S109: 3 | T109: 187 | U109: 4 | V109: 3 | W109: =IF('Cleaned Data'!V109<0,"Review",'Cleaned Data'!V109) -> 3 | X109: 2 | Y109: =IFERROR('Cleaned Data'!R109/'Cleaned Data'!L109,0) -> 97744.83 | Z109: =TEXT(EV_Sales[[#This Row],[Order_Date]],"mmm-yyyy") -> Nov-2025 | AA109: =MONTH(EV_Sales[[#This Row],[Order_Date]]) -> 11 | AB109: ="Q"&ROUNDUP(MONTH(EV_Sales[[#This Row],[Order_Date]])/3,0) -> Q4
A110: EV10109 | B110: 45951 | C110: Revolt | D110: RV1 | E110: Commuter | F110: Kolkata | G110: Fleet | H110: Cash | I110: =IF('Cleaned Data'!H110="Emi","EMI",'Cleaned Data'!H110) -> Cash | J110: Green | K110: SP-005 | L110: 1 | M110: 113303 | N110: 0.051 | O110: =IF(TRIM(N110&"")="","missing",N110) -> 0.051 | P110: 113303 | Q110: 5778.45 | R110: 107524.55 | S110: 4 | T110: 189 | U110: 3.6 | V110: 3 | W110: =IF('Cleaned Data'!V110<0,"Review",'Cleaned Data'!V110) -> 3 | X110: 2 | Y110: =IFERROR('Cleaned Data'!R110/'Cleaned Data'!L110,0) -> 107524.55 | Z110: =TEXT(EV_Sales[[#This Row],[Order_Date]],"mmm-yyyy") -> Oct-2025 | AA110: =MONTH(EV_Sales[[#This Row],[Order_Date]]) -> 10 | AB110: ="Q"&ROUNDUP(MONTH(EV_Sales[[#This Row],[Order_Date]])/3,0) -> Q4
... A162: EV10161 | B162: 46010 | C162: Ather | D162: Rizta | E162: Commuter | F162: Mumbai | G162: Corporate | H162: Cash | I162: =IF('Cleaned Data'!H162="Emi","EMI",'Cleaned Data'!H162) -> Cash | J162: Grey | K162: SP-024 | L162: 1 | M162: 142453 | N162: 0.041 | O162: =IF(TRIM(N162&"")="","missing",N162) -> 0.041 | P162: 142453 | Q162: 5840.57 | R162: 136612.43 | S162: 3 | T162: 169 | U162: 4 | V162: 7 | W162: =IF('Cleaned Data'!V162<0,"Review",'Cleaned Data'!V162) -> 7 | X162: 5 | Y162: =IFERROR('Cleaned Data'!R162/'Cleaned Data'!L162,0) -> 136612.43 | Z162: =TEXT(EV_Sales[[#This Row],[Order_Date]],"mmm-yyyy") -> Dec-2025 | AA162: =MONTH(EV_Sales[[#This Row],[Order_Date]]) -> 12 | AB162: ="Q"&ROUNDUP(MONTH(EV_Sales[[#This Row],[Order_Date]])/3,0) -> Q4
A163: EV10162 | B163: 45788 | C163: Ola Electric | D163: S1 Air | E163: Commuter | F163: Bengaluru | G163: Corporate | H163: Finance | I163: =IF('Cleaned Data'!H163="Emi","EMI",'Cleaned Data'!H163) -> Finance | J163: White | K163: SP-011 | L163: 4 | M163: 116559 | O163: =IF(TRIM(N163&"")="","missing",N163) -> missing | P163: 466236 | Q163: 20514.38 | R163: 445721.62 | S163: 2 | T163: 148 | U163: 3.9 | V163: 4 | W163: =IF('Cleaned Data'!V163<0,"Review",'Cleaned Data'!V163) -> 4 | X163: 3 | Y163: =IFERROR('Cleaned Data'!R163/'Cleaned Data'!L163,0) -> 111430.4 | Z163: =TEXT(EV_Sales[[#This Row],[Order_Date]],"mmm-yyyy") -> May-2025 | AA163: =MONTH(EV_Sales[[#This Row],[Order_Date]]) -> 5 | AB163: ="Q"&ROUNDUP(MONTH(EV_Sales[[#This Row],[Order_Date]])/3,0) -> Q2
A164: EV10163 | B164: 45833 | C164: Ather | D164: Rizta | E164: Performance | F164: Pune | G164: Dealer | H164: Cash | I164: =IF('Cleaned Data'!H164="Emi","EMI",'Cleaned Data'!H164) -> Cash | J164: Blue | K164: SP-004 | L164: 2 | M164: 140849 | N164: 0.101 | O164: =IF(TRIM(N164&"")="","missing",N164) -> 0.101 | P164: 281698 | Q164: 28451.5 | R164: 253246.5 | S164: 5 | T164: 194 | U164: 4.2 | V164: 4 | W164: =IF('Cleaned Data'!V164<0,"Review",'Cleaned Data'!V164) -> 4 | X164: 5 | Y164: =IFERROR('Cleaned Data'!R164/'Cleaned Data'!L164,0) -> 126623.25 | Z164: =TEXT(EV_Sales[[#This Row],[Order_Date]],"mmm-yyyy") -> Jun-2025 | AA164: =MONTH(EV_Sales[[#This Row],[Order_Date]]) -> 6 | AB164: ="Q"&ROUNDUP(MONTH(EV_Sales[[#This Row],[Order_Date]])/3,0) -> Q2
A165: EV10164 | B165: 45960 | C165: Ola Electric | D165: S1 Pro | E165: Performance | F165: Jaipur | G165: Corporate | H165: Cash | I165: =IF('Cleaned Data'!H165="Emi","EMI",'Cleaned Data'!H165) -> Cash | J165: White | K165: SP-019 | L165: 1 | M165: 135767 | N165: 0.023 | O165: =IF(TRIM(N165&"")="","missing",N165) -> 0.023 | P165: 135767 | Q165: 3122.64 | R165: 132644.36 | S165: 3 | T165: 170 | U165: 4.2 | V165: 13 | W165: =IF('Cleaned Data'!V165<0,"Review",'Cleaned Data'!V165) -> 13 | X165: 2 | Y165: =IFERROR('Cleaned Data'!R165/'Cleaned Data'!L165,0) -> 132644.36 | Z165: =TEXT(EV_Sales[[#This Row],[Order_Date]],"mmm-yyyy") -> Oct-2025 | AA165: =MONTH(EV_Sales[[#This Row],[Order_Date]]) -> 10 | AB165: ="Q"&ROUNDUP(MONTH(EV_Sales[[#This Row],[Order_Date]])/3,0) -> Q4
A166: EV10165 | B166: 45908 | C166: Ather | D166: 450S | E166: Premium | F166: Hyderabad | G166: Dealer | H166: Cash | I166: =IF('Cleaned Data'!H166="Emi","EMI",'Cleaned Data'!H166) -> Cash | J166: Green | K166: SP-026 | L166: 1 | M166: 125277 | N166: 0.059 | O166: =IF(TRIM(N166&"")="","missing",N166) -> 0.059 | P166: 125277 | Q166: 7391.34 | R166: 117885.66 | S166: 3 | T166: 157 | U166: 3.5 | V166: 4 | W166: =IF('Cleaned Data'!V166<0,"Review",'Cleaned Data'!V166) -> 4 | X166: 5 | Y166: =IFERROR('Cleaned Data'!R166/'Cleaned Data'!L166,0) -> 117885.66 | Z166: =TEXT(EV_Sales[[#This Row],[Order_Date]],"mmm-yyyy") -> Sep-2025 | AA166: =MONTH(EV_Sales[[#This Row],[Order_Date]]) -> 9 | AB166: ="Q"&ROUNDUP(MONTH(EV_Sales[[#This Row],[Order_Date]])/3,0) -> Q3
A167: EV10166 | B167: 45807 | C167: Ampere | D167: Magnus EX | E167: Performance | F167: Hyderabad | G167: Online | H167: Finance | I167: =IF('Cleaned Data'!H167="Emi","EMI",'Cleaned Data'!H167) -> Finance | J167: Grey | K167: SP-029 | L167: 4 | M167: 107900 | N167: 0.111 | O167: =IF(TRIM(N167&"")="","missing",N167) -> 0.111 | P167: 431600 | Q167: 47907.6 | R167: 383692.4 | S167: 4 | T167: 192 | U167: 3.9 | V167: 13 | W167: =IF('Cleaned Data'!V167<0,"Review",'Cleaned Data'!V167) -> 13 | X167: 5 | Y167: =IFERROR('Cleaned Data'!R167/'Cleaned Data'!L167,0) -> 95923.1 | Z167: =TEXT(EV_Sales[[#This Row],[Order_Date]],"mmm-yyyy") -> May-2025 | AA167: =MONTH(EV_Sales[[#This Row],[Order_Date]]) -> 5 | AB167: ="Q"&ROUNDUP(MONTH(EV_Sales[[#This Row],[Order_Date]])/3,0) -> Q2
A168: EV10167 | B168: 45943 | C168: Bajaj | D168: Chetak Urbane | E168: Commuter | F168: Pune | G168: Dealer | H168: Emi | I168: =IF('Cleaned Data'!H168="Emi","EMI",'Cleaned Data'!H168) -> EMI | J168: Grey | K168: SP-030 | L168: 1 | M168: 122328 | N168: 0.048 | O168: =IF(TRIM(N168&"")="","missing",N168) -> 0.048 | P168: 122328 | Q168: 5871.74 | R168: 116456.26 | S168: 4 | T168: 189 | U168: 4.8 | V168: 12 | W168: =IF('Cleaned Data'!V168<0,"Review",'Cleaned Data'!V168) -> 12 | X168: 3 | Y168: =IFERROR('Cleaned Data'!R168/'Cleaned Data'!L168,0) -> 116456.26 | Z168: =TEXT(EV_Sales[[#This Row],[Order_Date]],"mmm-yyyy") -> Oct-2025 | AA168: =MONTH(EV_Sales[[#This Row],[Order_Date]]) -> 10 | AB168: ="Q"&ROUNDUP(MONTH(EV_Sales[[#This Row],[Order_Date]])/3,0) -> Q4
A169: EV10168 | B169: 45925 | C169: Ather | D169: 450S | E169: Commuter | F169: Jaipur | G169: Fleet | H169: Emi | I169: =IF('Cleaned Data'!H169="Emi","EMI",'Cleaned Data'!H169) -> EMI | J169: Black | K169: SP-002 | L169: 2 | M169: 140316 | N169: 0.106 | O169: =IF(TRIM(N169&"")="","missing",N169) -> 0.106 | P169: 280632 | Q169: 29746.99 | R169: 250885.01 | S169: 4 | T169: 170 | U169: 4.2 | V169: 14 | W169: =IF('Cleaned Data'!V169<0,"Review",'Cleaned Data'!V169) -> 14 | X169: 2 | Y169: =IFERROR('Cleaned Data'!R169/'Cleaned Data'!L169,0) -> 125442.51 | Z169: =TEXT(EV_Sales[[#This Row],[Order_Date]],"mmm-yyyy") -> Sep-2025 | AA169: =MONTH(EV_Sales[[#This Row],[Order_Date]]) -> 9 | AB169: ="Q"&ROUNDUP(MONTH(EV_Sales[[#This Row],[Order_Date]])/3,0) -> Q3
A170: EV10169 | B170: 45722 | C170: Vida | D170: V2 | E170: Commuter | F170: Pune | G170: Fleet | H170: Cash | I170: =IF('Cleaned Data'!H170="Emi","EMI",'Cleaned Data'!H170) -> Cash | J170: Blue | K170: SP-006 | L170: 1 | M170: 114094 | N170: 0.028 | O170: =IF(TRIM(N170&"")="","missing",N170) -> 0.028 | P170: 114094 | Q170: 3194.63 | R170: 110899.37 | S170: 5 | T170: 186 | U170: Missing | V170: 4 | W170: =IF('Cleaned Data'!V170<0,"Review",'Cleaned Data'!V170) -> 4 | X170: 3 | Y170: =IFERROR('Cleaned Data'!R170/'Cleaned Data'!L170,0) -> 110899.37 | Z170: =TEXT(EV_Sales[[#This Row],[Order_Date]],"mmm-yyyy") -> Mar-2025 | AA170: =MONTH(EV_Sales[[#This Row],[Order_Date]]) -> 3 | AB170: ="Q"&ROUNDUP(MONTH(EV_Sales[[#This Row],[Order_Date]])/3,0) -> Q1
A171: EV10170 | B171: 45814 | C171: Bajaj | D171: Chetak Premium | E171: Commuter | F171: Delhi | G171: Fleet | H171: Emi | I171: =IF('Cleaned Data'!H171="Emi","EMI",'Cleaned Data'!H171) -> EMI | J171: Green | K171: SP-006 | L171: 2 | M171: 155204 | N171: 0.033 | O171: =IF(TRIM(N171&"")="","missing",N171) -> 0.033 | P171: 310408 | Q171: 10243.46 | R171: 300164.54 | S171: 3 | T171: 153 | U171: 3.7 | V171: 12 | W171: =IF('Cleaned Data'!V171<0,"Review",'Cleaned Data'!V171) -> 12 | X171: 5 | Y171: =IFERROR('Cleaned Data'!R171/'Cleaned Data'!L171,0) -> 150082.27 | Z171: =TEXT(EV_Sales[[#This Row],[Order_Date]],"mmm-yyyy") -> Jun-2025 | AA171: =MONTH(EV_Sales[[#This Row],[Order_Date]]) -> 6 | AB171: ="Q"&ROUNDUP(MONTH(EV_Sales[[#This Row],[Order_Date]])/3,0) -> Q2
A172: EV10171 | B172: 45867 | C172: Ampere | D172: Magnus EX | E172: Performance | F172: Hyderabad | G172: Fleet | H172: Cash | I172: =IF('Cleaned Data'!H172="Emi","EMI",'Cleaned Data'!H172) -> Cash | J172: Grey | K172: SP-029 | L172: 1 | M172: 110676 | N172: 0.025 | O172: =IF(TRIM(N172&"")="","missing",N172) -> 0.025 | P172: 110676 | Q172: 2766.9 | R172: 107909.1 | S172: 3 | T172: 161 | U172: 3.2 | V172: 9 | W172: =IF('Cleaned Data'!V172<0,"Review",'Cleaned Data'!V172) -> 9 | X172: 3 | Y172: =IFERROR('Cleaned Data'!R172/'Cleaned Data'!L172,0) -> 107909.1 | Z172: =TEXT(EV_Sales[[#This Row],[Order_Date]],"mmm-yyyy") -> Jul-2025 | AA172: =MONTH(EV_Sales[[#This Row],[Order_Date]]) -> 7 | AB172: ="Q"&ROUNDUP(MONTH(EV_Sales[[#This Row],[Order_Date]])/3,0) -> Q3
A173: EV10172 | B173: 45959 | C173: Ampere | D173: Magnus EX | E173: Premium | F173: Jaipur | G173: Dealer | H173: Cash | I173: =IF('Cleaned Data'!H173="Emi","EMI",'Cleaned Data'!H173) -> Cash | J173: Black | K173: SP-009 | L173: 1 | M173: 116233 | N173: 0.104 | O173: =IF(TRIM(N173&"")="","missing",N173) -> 0.104 | P173: 116233 | Q173: 12088.23 | R173: 104144.77 | S173: 3 | T173: 135 | U173: 3.5 | V173: 11 | W173: =IF('Cleaned Data'!V173<0,"Review",'Cleaned Data'!V173) -> 11 | X173: 5 | Y173: =IFERROR('Cleaned Data'!R173/'Cleaned Data'!L173,0) -> 104144.77 | Z173: =TEXT(EV_Sales[[#This Row],[Order_Date]],"mmm-yyyy") -> Oct-2025 | AA173: =MONTH(EV_Sales[[#This Row],[Order_Date]]) -> 10 | AB173: ="Q"&ROUNDUP(MONTH(EV_Sales[[#This Row],[Order_Date]])/3,0) -> Q4
A174: EV10173 | B174: 45964 | C174: Ather | D174: 450X | E174: Performance | F174: Ahmedabad | G174: Fleet | H174: Cash | I174: =IF('Cleaned Data'!H174="Emi","EMI",'Cleaned Data'!H174) -> Cash | J174: Grey | K174: SP-013 | L174: 4 | M174: 147968 | N174: 0.023 | O174: =IF(TRIM(N174&"")="","missing",N174) -> 0.023 | P174: 591872 | Q174: 13613.06 | R174: 578258.94 | S174: 4 | T174: 181 | U174: 3.8 | V174: 14 | W174: =IF('Cleaned Data'!V174<0,"Review",'Cleaned Data'!V174) -> 14 | X174: 2 | Y174: =IFERROR('Cleaned Data'!R174/'Cleaned Data'!L174,0) -> 144564.73 | Z174: =TEXT(EV_Sales[[#This Row],[Order_Date]],"mmm-yyyy") -> Nov-2025 | AA174: =MONTH(EV_Sales[[#This Row],[Order_Date]]) -> 11 | AB174: ="Q"&ROUNDUP(MONTH(EV_Sales[[#This Row],[Order_Date]])/3,0) -> Q4
A175: EV10174 | B175: 45897 | C175: Bajaj | D175: Chetak Premium | E175: Premium | F175: Mumbai | G175: Online | H175: Finance | I175: =IF('Cleaned Data'!H175="Emi","EMI",'Cleaned Data'!H175) -> Finance | J175: Black | K175: SP-004 | L175: 1 | M175: 156087 | N175: 0.115 | O175: =IF(TRIM(N175&"")="","missing",N175) -> 0.115 | P175: 156087 | Q175: 17950.01 | R175: 138136.99 | S175: 4 | T175: 191 | U175: 4.3 | V175: 2 | W175: =IF('Cleaned Data'!V175<0,"Review",'Cleaned Data'!V175) -> 2 | X175: 5 | Y175: =IFERROR('Cleaned Data'!R175/'Cleaned Data'!L175,0) -> 138136.99 | Z175: =TEXT(EV_Sales[[#This Row],[Order_Date]],"mmm-yyyy") -> Aug-2025 | AA175: =MONTH(EV_Sales[[#This Row],[Order_Date]]) -> 8 | AB175: ="Q"&ROUNDUP(MONTH(EV_Sales[[#This Row],[Order_Date]])/3,0) -> Q3
A176: EV10175 | B176: 45804 | C176: Ola Electric | D176: S1 Pro | E176: Commuter | F176: Jaipur | G176: Online | H176: Finance | I176: =IF('Cleaned Data'!H176="Emi","EMI",'Cleaned Data'!H176) -> Finance | J176: Blue | K176: SP-011 | L176: 2 | M176: 142371 | N176: 0.11 | O176: =IF(TRIM(N176&"")="","missing",N176) -> 0.11 | P176: 284742 | Q176: 31321.62 | R176: 253420.38 | S176: 3 | T176: 177 | U176: 3.7 | V176: 3 | W176: =IF('Cleaned Data'!V176<0,"Review",'Cleaned Data'!V176) -> 3 | X176: 5 | Y176: =IFERROR('Cleaned Data'!R176/'Cleaned Data'!L176,0) -> 126710.19 | Z176: =TEXT(EV_Sales[[#This Row],[Order_Date]],"mmm-yyyy") -> May-2025 | AA176: =MONTH(EV_Sales[[#This Row],[Order_Date]]) -> 5 | AB176: ="Q"&ROUNDUP(MONTH(EV_Sales[[#This Row],[Order_Date]])/3,0) -> Q2
A177: EV10176 | B177: 45867 | C177: Hero Electric | D177: Photon | E177: Performance | F177: Ahmedabad | G177: Online | H177: Cash | I177: =IF('Cleaned Data'!H177="Emi","EMI",'Cleaned Data'!H177) -> Cash | J177: Black | K177: SP-030 | L177: 1 | M177: 109963 | N177: 0.035 | O177: =IF(TRIM(N177&"")="","missing",N177) -> 0.035 | P177: 109963 | Q177: 3848.71 | R177: 106114.29 | S177: 3 | T177: 179 | U177: 4.4 | V177: 14 | W177: =IF('Cleaned Data'!V177<0,"Review",'Cleaned Data'!V177) -> 14 | X177: 3 | Y177: =IFERROR('Cleaned Data'!R177/'Cleaned Data'!L177,0) -> 106114.29 | Z177: =TEXT(EV_Sales[[#This Row],[Order_Date]],"mmm-yyyy") -> Jul-2025 | AA177: =MONTH(EV_Sales[[#This Row],[Order_Date]]) -> 7 | AB177: ="Q"&ROUNDUP(MONTH(EV_Sales[[#This Row],[Order_Date]])/3,0) -> Q3
A178: EV10177 | B178: 45892 | C178: Bajaj | D178: Chetak Premium | E178: Premium | F178: Chennai | G178: Online | H178: Emi | I178: =IF('Cleaned Data'!H178="Emi","EMI",'Cleaned Data'!H178) -> EMI | J178: White | K178: SP-004 | L178: 1 | M178: 153121 | N178: 0.024 | O178: =IF(TRIM(N178&"")="","missing",N178) -> 0.024 | P178: 153121 | Q178: 3674.9 | R178: 149446.1 | S178: 3 | T178: 140 | U178: 4.4 | V178: 8 | W178: =IF('Cleaned Data'!V178<0,"Review",'Cleaned Data'!V178) -> 8 | X178: 2 | Y178: =IFERROR('Cleaned Data'!R178/'Cleaned Data'!L178,0) -> 149446.1 | Z178: =TEXT(EV_Sales[[#This Row],[Order_Date]],"mmm-yyyy") -> Aug-2025 | AA178: =MONTH(EV_Sales[[#This Row],[Order_Date]]) -> 8 | AB178: ="Q"&ROUNDUP(MONTH(EV_Sales[[#This Row],[Order_Date]])/3,0) -> Q3
A179: EV10178 | B179: 45730 | C179: TVS | D179: iQube | E179: Performance | F179: Ahmedabad | G179: Corporate | H179: Finance | I179: =IF('Cleaned Data'!H179="Emi","EMI",'Cleaned Data'!H179) -> Finance | J179: Blue | K179: SP-025 | L179: 1 | M179: 131307 | N179: 0.065 | O179: =IF(TRIM(N179&"")="","missing",N179) -> 0.065 | P179: 131307 | Q179: 8534.95 | R179: 122772.05 | S179: 4 | T179: 185 | U179: 4.2 | V179: 10 | W179: =IF('Cleaned Data'!V179<0,"Review",'Cleaned Data'!V179) -> 10 | X179: 5 | Y179: =IFERROR('Cleaned Data'!R179/'Cleaned Data'!L179,0) -> 122772.05 | Z179: =TEXT(EV_Sales[[#This Row],[Order_Date]],"mmm-yyyy") -> Mar-2025 | AA179: =MONTH(EV_Sales[[#This Row],[Order_Date]]) -> 3 | AB179: ="Q"&ROUNDUP(MONTH(EV_Sales[[#This Row],[Order_Date]])/3,0) -> Q1
A180: EV10179 | B180: 45824 | C180: Ampere | D180: Primus | E180: Performance | F180: Delhi | G180: Dealer | H180: Finance | I180: =IF('Cleaned Data'!H180="Emi","EMI",'Cleaned Data'!H180) -> Finance | J180: Grey | K180: SP-008 | L180: 2 | M180: 144478 | N180: 0.085 | O180: =IF(TRIM(N180&"")="","missing",N180) -> 0.085 | P180: 288956 | Q180: 24561.26 | R180: 264394.74 | S180: 2 | T180: 148 | U180: 3.1 | V180: 3 | W180: =IF('Cleaned Data'!V180<0,"Review",'Cleaned Data'!V180) -> 3 | X180: 5 | Y180: =IFERROR('Cleaned Data'!R180/'Cleaned Data'!L180,0) -> 132197.37 | Z180: =TEXT(EV_Sales[[#This Row],[Order_Date]],"mmm-yyyy") -> Jun-2025 | AA180: =MONTH(EV_Sales[[#This Row],[Order_Date]]) -> 6 | AB180: ="Q"&ROUNDUP(MONTH(EV_Sales[[#This Row],[Order_Date]])/3,0) -> Q2
A181: EV10180 | B181: 45978 | C181: Ola Electric | D181: S1 Air | E181: Performance | F181: Pune | G181: Corporate | H181: Emi | I181: =IF('Cleaned Data'!H181="Emi","EMI",'Cleaned Data'!H181) -> EMI | J181: White | K181: SP-019 | L181: 1 | M181: 110794 | N181: 0.117 | O181: =IF(TRIM(N181&"")="","missing",N181) -> 0.117 | P181: 110794 | Q181: 12962.9 | R181: 97831.1 | S181: 3 | T181: 164 | U181: 4.3 | V181: 14 | W181: =IF('Cleaned Data'!V181<0,"Review",'Cleaned Data'!V181) -> 14 | X181: 3 | Y181: =IFERROR('Cleaned Data'!R181/'Cleaned Data'!L181,0) -> 97831.1 | Z181: =TEXT(EV_Sales[[#This Row],[Order_Date]],"mmm-yyyy") -> Nov-2025 | AA181: =MONTH(EV_Sales[[#This Row],[Order_Date]]) -> 11 | AB181: ="Q"&ROUNDUP(MONTH(EV_Sales[[#This Row],[Order_Date]])/3,0) -> Q4
A182: EV10181 | B182: 45972 | C182: Ola Electric | D182: S1 Air | E182: Premium | F182: Hyderabad | G182: Online | H182: Cash | I182: =IF('Cleaned Data'!H182="Emi","EMI",'Cleaned Data'!H182) -> Cash | J182: Black | K182: SP-029 | L182: 1 | M182: 115954 | N182: 0.033 | O182: =IF(TRIM(N182&"")="","missing",N182) -> 0.033 | P182: 115954 | Q182: 3826.48 | R182: 112127.52 | S182: 5 | T182: 183 | U182: 3.4 | V182: 4 | W182: =IF('Cleaned Data'!V182<0,"Review",'Cleaned Data'!V182) -> 4 | X182: 5 | Y182: =IFERROR('Cleaned Data'!R182/'Cleaned Data'!L182,0) -> 112127.52 | Z182: =TEXT(EV_Sales[[#This Row],[Order_Date]],"mmm-yyyy") -> Nov-2025 | AA182: =MONTH(EV_Sales[[#This Row],[Order_Date]]) -> 11 | AB182: ="Q"&ROUNDUP(MONTH(EV_Sales[[#This Row],[Order_Date]])/3,0) -> Q4
... A185: EV10184 | B185: 45930 | C185: Ola Electric | D185: S1 X | E185: Commuter | F185: Chennai | G185: Fleet | H185: Finance | I185: =IF('Cleaned Data'!H185="Emi","EMI",'Cleaned Data'!H185) -> Finance | J185: Blue | K185: SP-027 | L185: 2 | M185: 103117 | N185: 0.053 | O185: =IF(TRIM(N185&"")="","missing",N185) -> 0.053 | P185: 206234 | Q185: 10930.4 | R185: 195303.6 | S185: 4 | T185: 202 | U185: 4 | V185: 9 | W185: =IF('Cleaned Data'!V185<0,"Review",'Cleaned Data'!V185) -> 9 | X185: 2 | Y185: =IFERROR('Cleaned Data'!R185/'Cleaned Data'!L185,0) -> 97651.8 | Z185: =TEXT(EV_Sales[[#This Row],[Order_Date]],"mmm-yyyy") -> Sep-2025 | AA185: =MONTH(EV_Sales[[#This Row],[Order_Date]]) -> 9 | AB185: ="Q"&ROUNDUP(MONTH(EV_Sales[[#This Row],[Order_Date]])/3,0) -> Q3
A186: EV10185 | B186: 45924 | C186: Hero Electric | D186: Photon | E186: Premium | F186: Kochi | G186: Fleet | H186: Finance | I186: =IF('Cleaned Data'!H186="Emi","EMI",'Cleaned Data'!H186) -> Finance | J186: Black | K186: SP-019 | L186: 1 | M186: 115481 | N186: 0.024 | O186: =IF(TRIM(N186&"")="","missing",N186) -> 0.024 | P186: 115481 | Q186: 2771.54 | R186: 112709.46 | S186: 4 | T186: 173 | U186: Missing | V186: 9 | W186: =IF('Cleaned Data'!V186<0,"Review",'Cleaned Data'!V186) -> 9 | X186: 2 | Y186: =IFERROR('Cleaned Data'!R186/'Cleaned Data'!L186,0) -> 112709.46 | Z186: =TEXT(EV_Sales[[#This Row],[Order_Date]],"mmm-yyyy") -> Sep-2025 | AA186: =MONTH(EV_Sales[[#This Row],[Order_Date]]) -> 9 | AB186: ="Q"&ROUNDUP(MONTH(EV_Sales[[#This Row],[Order_Date]])/3,0) -> Q3
A187: EV10186 | B187: 45961 | C187: TVS | D187: X | E187: Performance | F187: Jaipur | G187: Corporate | H187: Finance | I187: =IF('Cleaned Data'!H187="Emi","EMI",'Cleaned Data'!H187) -> Finance | J187: Black | K187: SP-019 | L187: 1 | M187: 188216 | N187: 0.069 | O187: =IF(TRIM(N187&"")="","missing",N187) -> 0.069 | P187: 188216 | Q187: 12986.9 | R187: 175229.1 | S187: 3 | T187: 203 | U187: 3.5 | V187: 9 | W187: =IF('Cleaned Data'!V187<0,"Review",'Cleaned Data'!V187) -> 9 | X187: 5 | Y187: =IFERROR('Cleaned Data'!R187/'Cleaned Data'!L187,0) -> 175229.1 | Z187: =TEXT(EV_Sales[[#This Row],[Order_Date]],"mmm-yyyy") -> Oct-2025 | AA187: =MONTH(EV_Sales[[#This Row],[Order_Date]]) -> 10 | AB187: ="Q"&ROUNDUP(MONTH(EV_Sales[[#This Row],[Order_Date]])/3,0) -> Q4
A188: EV10187 | B188: 45876 | C188: Hero Electric | D188: Photon | E188: Performance | F188: Pune | G188: Corporate | H188: Emi | I188: =IF('Cleaned Data'!H188="Emi","EMI",'Cleaned Data'!H188) -> EMI | J188: Grey | K188: SP-013 | L188: 1 | M188: 121423 | N188: 0.096 | O188: =IF(TRIM(N188&"")="","missing",N188) -> 0.096 | P188: 121423 | Q188: 11656.61 | R188: 109766.39 | S188: 4 | T188: 195 | U188: 4 | V188: 9 | W188: =IF('Cleaned Data'!V188<0,"Review",'Cleaned Data'!V188) -> 9 | X188: 5 | Y188: =IFERROR('Cleaned Data'!R188/'Cleaned Data'!L188,0) -> 109766.39 | Z188: =TEXT(EV_Sales[[#This Row],[Order_Date]],"mmm-yyyy") -> Aug-2025 | AA188: =MONTH(EV_Sales[[#This Row],[Order_Date]]) -> 8 | AB188: ="Q"&ROUNDUP(MONTH(EV_Sales[[#This Row],[Order_Date]])/3,0) -> Q3
A189: EV10188 | B189: 45846 | C189: Revolt | D189: RV1 | E189: Commuter | F189: Mumbai | G189: Dealer | H189: Emi | I189: =IF('Cleaned Data'!H189="Emi","EMI",'Cleaned Data'!H189) -> EMI | J189: Green | K189: SP-025 | L189: 4 | M189: 113121 | N189: 0.068 | O189: =IF(TRIM(N189&"")="","missing",N189) -> 0.068 | P189: 452484 | Q189: 30768.91 | R189: 421715.09 | S189: 4 | T189: 193 | U189: 4.6 | V189: 11 | W189: =IF('Cleaned Data'!V189<0,"Review",'Cleaned Data'!V189) -> 11 | X189: 3 | Y189: =IFERROR('Cleaned Data'!R189/'Cleaned Data'!L189,0) -> 105428.77 | Z189: =TEXT(EV_Sales[[#This Row],[Order_Date]],"mmm-yyyy") -> Jul-2025 | AA189: =MONTH(EV_Sales[[#This Row],[Order_Date]]) -> 7 | AB189: ="Q"&ROUNDUP(MONTH(EV_Sales[[#This Row],[Order_Date]])/3,0) -> Q3
A190: EV10189 | B190: 45820 | C190: Ampere | D190: Magnus EX | E190: Commuter | F190: Unknown | G190: Corporate | H190: Cash | I190: =IF('Cleaned Data'!H190="Emi","EMI",'Cleaned Data'!H190) -> Cash | J190: Red | K190: SP-003 | L190: 5 | M190: 113823 | N190: 0.103 | O190: =IF(TRIM(N190&"")="","missing",N190) -> 0.103 | P190: 569115 | Q190: 58618.84 | R190: 510496.16 | S190: 3 | T190: 170 | U190: 4.4 | V190: 6 | W190: =IF('Cleaned Data'!V190<0,"Review",'Cleaned Data'!V190) -> 6 | X190: 2 | Y190: =IFERROR('Cleaned Data'!R190/'Cleaned Data'!L190,0) -> 102099.23 | Z190: =TEXT(EV_Sales[[#This Row],[Order_Date]],"mmm-yyyy") -> Jun-2025 | AA190: =MONTH(EV_Sales[[#This Row],[Order_Date]]) -> 6 | AB190: ="Q"&ROUNDUP(MONTH(EV_Sales[[#This Row],[Order_Date]])/3,0) -> Q2
A191: EV10190 | B191: 45761 | C191: Ola Electric | D191: S1 X | E191: Premium | F191: Bengaluru | G191: Corporate | H191: Finance | I191: =IF('Cleaned Data'!H191="Emi","EMI",'Cleaned Data'!H191) -> Finance | J191: White | K191: SP-008 | L191: 1 | M191: 109330 | N191: 0.048 | O191: =IF(TRIM(N191&"")="","missing",N191) -> 0.048 | P191: 109330 | Q191: 5247.84 | R191: 104082.16 | S191: 4 | T191: 207 | U191: 4.5 | V191: 14 | W191: =IF('Cleaned Data'!V191<0,"Review",'Cleaned Data'!V191) -> 14 | X191: 2 | Y191: =IFERROR('Cleaned Data'!R191/'Cleaned Data'!L191,0) -> 104082.16 | Z191: =TEXT(EV_Sales[[#This Row],[Order_Date]],"mmm-yyyy") -> Apr-2025 | AA191: =MONTH(EV_Sales[[#This Row],[Order_Date]]) -> 4 | AB191: ="Q"&ROUNDUP(MONTH(EV_Sales[[#This Row],[Order_Date]])/3,0) -> Q2
A192: EV10191 | B192: 45819 | C192: Ather | D192: Rizta | E192: Performance | F192: Bengaluru | G192: Fleet | H192: Emi | I192: =IF('Cleaned Data'!H192="Emi","EMI",'Cleaned Data'!H192) -> EMI | J192: Green | K192: SP-024 | L192: 3 | M192: 140263 | N192: 0.025 | O192: =IF(TRIM(N192&"")="","missing",N192) -> 0.025 | P192: 420789 | Q192: 10519.73 | R192: 410269.27 | S192: 2 | T192: 126 | U192: 3.8 | V192: 13 | W192: =IF('Cleaned Data'!V192<0,"Review",'Cleaned Data'!V192) -> 13 | X192: 3 | Y192: =IFERROR('Cleaned Data'!R192/'Cleaned Data'!L192,0) -> 136756.42 | Z192: =TEXT(EV_Sales[[#This Row],[Order_Date]],"mmm-yyyy") -> Jun-2025 | AA192: =MONTH(EV_Sales[[#This Row],[Order_Date]]) -> 6 | AB192: ="Q"&ROUNDUP(MONTH(EV_Sales[[#This Row],[Order_Date]])/3,0) -> Q2
A193: EV10192 | B193: 45684 | C193: Ampere | D193: Magnus EX | E193: Performance | F193: Delhi | G193: Corporate | H193: Emi | I193: =IF('Cleaned Data'!H193="Emi","EMI",'Cleaned Data'!H193) -> EMI | J193: Green | K193: SP-010 | L193: 1 | M193: 112382 | N193: 0.104 | O193: =IF(TRIM(N193&"")="","missing",N193) -> 0.104 | P193: 112382 | Q193: 11687.73 | R193: 100694.27 | S193: 4 | T193: 177 | U193: 3.5 | V193: 10 | W193: =IF('Cleaned Data'!V193<0,"Review",'Cleaned Data'!V193) -> 10 | X193: 3 | Y193: =IFERROR('Cleaned Data'!R193/'Cleaned Data'!L193,0) -> 100694.27 | Z193: =TEXT(EV_Sales[[#This Row],[Order_Date]],"mmm-yyyy") -> Jan-2025 | AA193: =MONTH(EV_Sales[[#This Row],[Order_Date]]) -> 1 | AB193: ="Q"&ROUNDUP(MONTH(EV_Sales[[#This Row],[Order_Date]])/3,0) -> Q1
A194: EV10193 | B194: 45709 | C194: Ola Electric | D194: S1 Air | E194: Performance | F194: Kolkata | G194: Fleet | H194: Finance | I194: =IF('Cleaned Data'!H194="Emi","EMI",'Cleaned Data'!H194) -> Finance | J194: Red | K194: SP-023 | L194: 2 | M194: 116573 | N194: 0.066 | O194: =IF(TRIM(N194&"")="","missing",N194) -> 0.066 | P194: 233146 | Q194: 15387.64 | R194: 217758.36 | S194: 3 | T194: 150 | U194: 3.6 | V194: 5 | W194: =IF('Cleaned Data'!V194<0,"Review",'Cleaned Data'!V194) -> 5 | X194: 2 | Y194: =IFERROR('Cleaned Data'!R194/'Cleaned Data'!L194,0) -> 108879.18 | Z194: =TEXT(EV_Sales[[#This Row],[Order_Date]],"mmm-yyyy") -> Feb-2025 | AA194: =MONTH(EV_Sales[[#This Row],[Order_Date]]) -> 2 | AB194: ="Q"&ROUNDUP(MONTH(EV_Sales[[#This Row],[Order_Date]])/3,0) -> Q1
A195: EV10194 | B195: 45947 | C195: Revolt | D195: RV1 | E195: Commuter | F195: Kolkata | G195: Fleet | H195: Finance | I195: =IF('Cleaned Data'!H195="Emi","EMI",'Cleaned Data'!H195) -> Finance | J195: Black | K195: SP-006 | L195: 1 | M195: 123376 | N195: 0.025 | O195: =IF(TRIM(N195&"")="","missing",N195) -> 0.025 | P195: 123376 | Q195: 3084.4 | R195: 120291.6 | S195: 4 | T195: 174 | U195: 4.1 | V195: 7 | W195: =IF('Cleaned Data'!V195<0,"Review",'Cleaned Data'!V195) -> 7 | X195: 3 | Y195: =IFERROR('Cleaned Data'!R195/'Cleaned Data'!L195,0) -> 120291.6 | Z195: =TEXT(EV_Sales[[#This Row],[Order_Date]],"mmm-yyyy") -> Oct-2025 | AA195: =MONTH(EV_Sales[[#This Row],[Order_Date]]) -> 10 | AB195: ="Q"&ROUNDUP(MONTH(EV_Sales[[#This Row],[Order_Date]])/3,0) -> Q4
A196: EV10195 | B196: 45977 | C196: Hero Electric | D196: Photon | E196: Performance | F196: Bengaluru | G196: Dealer | H196: Emi | I196: =IF('Cleaned Data'!H196="Emi","EMI",'Cleaned Data'!H196) -> EMI | J196: Black | K196: SP-006 | L196: 1 | M196: 109740 | N196: 0.056 | O196: =IF(TRIM(N196&"")="","missing",N196) -> 0.056 | P196: 109740 | Q196: 6145.44 | R196: 103594.56 | S196: 3 | T196: 158 | U196: 4.5 | V196: 5 | W196: =IF('Cleaned Data'!V196<0,"Review",'Cleaned Data'!V196) -> 5 | X196: 3 | Y196: =IFERROR('Cleaned Data'!R196/'Cleaned Data'!L196,0) -> 103594.56 | Z196: =TEXT(EV_Sales[[#This Row],[Order_Date]],"mmm-yyyy") -> Nov-2025 | AA196: =MONTH(EV_Sales[[#This Row],[Order_Date]]) -> 11 | AB196: ="Q"&ROUNDUP(MONTH(EV_Sales[[#This Row],[Order_Date]])/3,0) -> Q4
A197: EV10196 | B197: 45836 | C197: Vida | D197: V2 | E197: Performance | F197: Chennai | G197: Dealer | H197: Emi | I197: =IF('Cleaned Data'!H197="Emi","EMI",'Cleaned Data'!H197) -> EMI | J197: Grey | K197: SP-005 | L197: 1 | M197: 113980 | N197: 0.069 | O197: =IF(TRIM(N197&"")="","missing",N197) -> 0.069 | P197: 113980 | Q197: 7864.62 | R197: 106115.38 | S197: 3 | T197: 181 | U197: 4.5 | V197: 11 | W197: =IF('Cleaned Data'!V197<0,"Review",'Cleaned Data'!V197) -> 11 | X197: 5 | Y197: =IFERROR('Cleaned Data'!R197/'Cleaned Data'!L197,0) -> 106115.38 | Z197: =TEXT(EV_Sales[[#This Row],[Order_Date]],"mmm-yyyy") -> Jun-2025 | AA197: =MONTH(EV_Sales[[#This Row],[Order_Date]]) -> 6 | AB197: ="Q"&ROUNDUP(MONTH(EV_Sales[[#This Row],[Order_Date]])/3,0) -> Q2
A198: EV10197 | B198: 45930 | C198: Ather | D198: Rizta | E198: Performance | F198: Mumbai | G198: Fleet | H198: Finance | I198: =IF('Cleaned Data'!H198="Emi","EMI",'Cleaned Data'!H198) -> Finance | J198: Blue | K198: SP-012 | L198: 2 | M198: 144741 | N198: 0.047 | O198: =IF(TRIM(N198&"")="","missing",N198) -> 0.047 | P198: 289482 | Q198: 13605.65 | R198: 275876.35 | S198: 3 | T198: 163 | U198: 3.7 | V198: 8 | W198: =IF('Cleaned Data'!V198<0,"Review",'Cleaned Data'!V198) -> 8 | X198: 2 | Y198: =IFERROR('Cleaned Data'!R198/'Cleaned Data'!L198,0) -> 137938.17 | Z198: =TEXT(EV_Sales[[#This Row],[Order_Date]],"mmm-yyyy") -> Sep-2025 | AA198: =MONTH(EV_Sales[[#This Row],[Order_Date]]) -> 9 | AB198: ="Q"&ROUNDUP(MONTH(EV_Sales[[#This Row],[Order_Date]])/3,0) -> Q3
... A201: EV10200 | B201: 45775 | C201: Ather | D201: 450X | E201: Commuter | F201: Hyderabad | G201: Online | H201: Finance | I201: =IF('Cleaned Data'!H201="Emi","EMI",'Cleaned Data'!H201) -> Finance | J201: Blue | K201: SP-025 | L201: 3 | M201: 147339 | N201: 0.03 | O201: =IF(TRIM(N201&"")="","missing",N201) -> 0.03 | P201: 442017 | Q201: 13260.51 | R201: 428756.49 | S201: 4 | T201: 185 | U201: 4 | V201: 3 | W201: =IF('Cleaned Data'!V201<0,"Review",'Cleaned Data'!V201) -> 3 | X201: 3 | Y201: =IFERROR('Cleaned Data'!R201/'Cleaned Data'!L201,0) -> 142918.83 | Z201: =TEXT(EV_Sales[[#This Row],[Order_Date]],"mmm-yyyy") -> Apr-2025 | AA201: =MONTH(EV_Sales[[#This Row],[Order_Date]]) -> 4 | AB201: ="Q"&ROUNDUP(MONTH(EV_Sales[[#This Row],[Order_Date]])/3,0) -> Q2
A202: EV10201 | B202: 45759 | C202: TVS | D202: iQube | E202: Performance | F202: Delhi | G202: Fleet | H202: Finance | I202: =IF('Cleaned Data'!H202="Emi","EMI",'Cleaned Data'!H202) -> Finance | J202: Red | K202: SP-027 | L202: 2 | M202: 127914 | O202: =IF(TRIM(N202&"")="","missing",N202) -> missing | P202: 255828 | Q202: 5372.39 | R202: 250455.61 | S202: 3 | T202: 164 | U202: 4.3 | V202: 7 | W202: =IF('Cleaned Data'!V202<0,"Review",'Cleaned Data'!V202) -> 7 | X202: 2 | Y202: =IFERROR('Cleaned Data'!R202/'Cleaned Data'!L202,0) -> 125227.8 | Z202: =TEXT(EV_Sales[[#This Row],[Order_Date]],"mmm-yyyy") -> Apr-2025 | AA202: =MONTH(EV_Sales[[#This Row],[Order_Date]]) -> 4 | AB202: ="Q"&ROUNDUP(MONTH(EV_Sales[[#This Row],[Order_Date]])/3,0) -> Q2
A203: EV10202 | B203: 45827 | C203: Ampere | D203: Magnus EX | E203: Premium | F203: Chennai | G203: Fleet | H203: Cash | I203: =IF('Cleaned Data'!H203="Emi","EMI",'Cleaned Data'!H203) -> Cash | J203: Red | K203: SP-015 | L203: 3 | M203: 115830 | N203: 0.032 | O203: =IF(TRIM(N203&"")="","missing",N203) -> 0.032 | P203: 347490 | Q203: 11119.68 | R203: 336370.32 | S203: 3 | T203: 165 | U203: 4.8 | V203: 5 | W203: =IF('Cleaned Data'!V203<0,"Review",'Cleaned Data'!V203) -> 5 | X203: 2 | Y203: =IFERROR('Cleaned Data'!R203/'Cleaned Data'!L203,0) -> 112123.44 | Z203: =TEXT(EV_Sales[[#This Row],[Order_Date]],"mmm-yyyy") -> Jun-2025 | AA203: =MONTH(EV_Sales[[#This Row],[Order_Date]]) -> 6 | AB203: ="Q"&ROUNDUP(MONTH(EV_Sales[[#This Row],[Order_Date]])/3,0) -> Q2
A204: EV10203 | B204: 45817 | C204: TVS | D204: iQube | E204: Commuter | F204: Mumbai | G204: Online | H204: Cash | I204: =IF('Cleaned Data'!H204="Emi","EMI",'Cleaned Data'!H204) -> Cash | J204: Red | K204: SP-023 | L204: 4 | M204: 131205 | N204: 0.098 | O204: =IF(TRIM(N204&"")="","missing",N204) -> 0.098 | P204: 524820 | Q204: 51432.36 | R204: 473387.64 | S204: 3 | T204: 144 | U204: 3.7 | V204: 4 | W204: =IF('Cleaned Data'!V204<0,"Review",'Cleaned Data'!V204) -> 4 | X204: 2 | Y204: =IFERROR('Cleaned Data'!R204/'Cleaned Data'!L204,0) -> 118346.91 | Z204: =TEXT(EV_Sales[[#This Row],[Order_Date]],"mmm-yyyy") -> Jun-2025 | AA204: =MONTH(EV_Sales[[#This Row],[Order_Date]]) -> 6 | AB204: ="Q"&ROUNDUP(MONTH(EV_Sales[[#This Row],[Order_Date]])/3,0) -> Q2
A205: EV10204 | B205: 45661 | C205: Bajaj | D205: Chetak Urbane | E205: Commuter | F205: Delhi | G205: Corporate | H205: Finance | I205: =IF('Cleaned Data'!H205="Emi","EMI",'Cleaned Data'!H205) -> Finance | J205: Red | K205: SP-007 | L205: 5 | M205: 128637 | N205: 0.099 | O205: =IF(TRIM(N205&"")="","missing",N205) -> 0.099 | P205: 643185 | Q205: 63675.32 | R205: 579509.68 | S205: 5 | T205: 206 | U205: 4.1 | V205: 13 | W205: =IF('Cleaned Data'!V205<0,"Review",'Cleaned Data'!V205) -> 13 | X205: 3 | Y205: =IFERROR('Cleaned Data'!R205/'Cleaned Data'!L205,0) -> 115901.94 | Z205: =TEXT(EV_Sales[[#This Row],[Order_Date]],"mmm-yyyy") -> Jan-2025 | AA205: =MONTH(EV_Sales[[#This Row],[Order_Date]]) -> 1 | AB205: ="Q"&ROUNDUP(MONTH(EV_Sales[[#This Row],[Order_Date]])/3,0) -> Q1
A206: EV10205 | B206: 45683 | C206: Ola Electric | D206: S1 Pro | E206: Performance | F206: Delhi | G206: Dealer | H206: Emi | I206: =IF('Cleaned Data'!H206="Emi","EMI",'Cleaned Data'!H206) -> EMI | J206: Red | K206: SP-006 | L206: 3 | M206: 137776 | N206: 0.048 | O206: =IF(TRIM(N206&"")="","missing",N206) -> 0.048 | P206: 413328 | Q206: 19839.74 | R206: 393488.26 | S206: 5 | T206: 210 | U206: 4.1 | V206: 13 | W206: =IF('Cleaned Data'!V206<0,"Review",'Cleaned Data'!V206) -> 13 | X206: 5 | Y206: =IFERROR('Cleaned Data'!R206/'Cleaned Data'!L206,0) -> 131162.75 | Z206: =TEXT(EV_Sales[[#This Row],[Order_Date]],"mmm-yyyy") -> Jan-2025 | AA206: =MONTH(EV_Sales[[#This Row],[Order_Date]]) -> 1 | AB206: ="Q"&ROUNDUP(MONTH(EV_Sales[[#This Row],[Order_Date]])/3,0) -> Q1
A207: EV10206 | B207: 45845 | C207: Vida | D207: V2 | E207: Premium | F207: Delhi | G207: Online | H207: Finance | I207: =IF('Cleaned Data'!H207="Emi","EMI",'Cleaned Data'!H207) -> Finance | J207: Blue | K207: SP-002 | L207: 2 | M207: 104333 | N207: 0.089 | O207: =IF(TRIM(N207&"")="","missing",N207) -> 0.089 | P207: 208666 | Q207: 18571.27 | R207: 190094.73 | S207: 4 | T207: 181 | U207: 4.4 | V207: 10 | W207: =IF('Cleaned Data'!V207<0,"Review",'Cleaned Data'!V207) -> 10 | X207: 5 | Y207: =IFERROR('Cleaned Data'!R207/'Cleaned Data'!L207,0) -> 95047.365 | Z207: =TEXT(EV_Sales[[#This Row],[Order_Date]],"mmm-yyyy") -> Jul-2025 | AA207: =MONTH(EV_Sales[[#This Row],[Order_Date]]) -> 7 | AB207: ="Q"&ROUNDUP(MONTH(EV_Sales[[#This Row],[Order_Date]])/3,0) -> Q3
A208: EV10207 | B208: 45718 | C208: Revolt | D208: RV1 | E208: Premium | F208: Bengaluru | G208: Online | H208: Finance | I208: =IF('Cleaned Data'!H208="Emi","EMI",'Cleaned Data'!H208) -> Finance | J208: Grey | K208: SP-008 | L208: 5 | M208: 128966 | N208: 0.082 | O208: =IF(TRIM(N208&"")="","missing",N208) -> 0.082 | P208: 644830 | Q208: 52876.06 | R208: 591953.94 | S208: 5 | T208: 203 | U208: 4.8 | V208: 14 | W208: =IF('Cleaned Data'!V208<0,"Review",'Cleaned Data'!V208) -> 14 | X208: 5 | Y208: =IFERROR('Cleaned Data'!R208/'Cleaned Data'!L208,0) -> 118390.79 | Z208: =TEXT(EV_Sales[[#This Row],[Order_Date]],"mmm-yyyy") -> Mar-2025 | AA208: =MONTH(EV_Sales[[#This Row],[Order_Date]]) -> 3 | AB208: ="Q"&ROUNDUP(MONTH(EV_Sales[[#This Row],[Order_Date]])/3,0) -> Q1
A209: EV10208 | B209: 45892 | C209: Bajaj | D209: Chetak Premium | E209: Performance | F209: Kochi | G209: Online | H209: Emi | I209: =IF('Cleaned Data'!H209="Emi","EMI",'Cleaned Data'!H209) -> Emi | J209: Red | K209: SP-011 | L209: 2 | M209: 143876 | N209: 0.119 | O209: =IF(TRIM(N209&"")="","missing",N209) -> 0.119 | P209: 287752 | Q209: 34242.49 | R209: 253509.51 | S209: 4 | T209: 201 | U209: 3.6 | V209: 10 | W209: =IF('Cleaned Data'!V209<0,"Review",'Cleaned Data'!V209) -> 10 | X209: 5 | Y209: =IFERROR('Cleaned Data'!R209/'Cleaned Data'!L209,0) -> 126754.76 | Z209: =TEXT(EV_Sales[[#This Row],[Order_Date]],"mmm-yyyy") -> Aug-2025 | AA209: =MONTH(EV_Sales[[#This Row],[Order_Date]]) -> 8 | AB209: ="Q"&ROUNDUP(MONTH(EV_Sales[[#This Row],[Order_Date]])/3,0) -> Q3
A210: EV10209 | B210: 45931 | C210: Hero Electric | D210: Optima | E210: Premium | F210: Delhi | G210: Corporate | H210: Emi | I210: =IF('Cleaned Data'!H210="Emi","EMI",'Cleaned Data'!H210) -> EMI | J210: Grey | K210: SP-016 | L210: 2 | M210: 99774 | N210: 0.082 | O210: =IF(TRIM(N210&"")="","missing",N210) -> 0.082 | P210: 199548 | Q210: 16362.94 | R210: 183185.06 | S210: 5 | T210: 206 | U210: 3.8 | V210: 12 | W210: =IF('Cleaned Data'!V210<0,"Review",'Cleaned Data'!V210) -> 12 | X210: 2 | Y210: =IFERROR('Cleaned Data'!R210/'Cleaned Data'!L210,0) -> 91592.53 | Z210: =TEXT(EV_Sales[[#This Row],[Order_Date]],"mmm-yyyy") -> Oct-2025 | AA210: =MONTH(EV_Sales[[#This Row],[Order_Date]]) -> 10 | AB210: ="Q"&ROUNDUP(MONTH(EV_Sales[[#This Row],[Order_Date]])/3,0) -> Q4
A211: EV10210 | B211: 45904 | C211: Ola Electric | D211: S1 Air | E211: Premium | F211: Pune | G211: Dealer | H211: Finance | I211: =IF('Cleaned Data'!H211="Emi","EMI",'Cleaned Data'!H211) -> Finance | J211: Red | K211: SP-009 | L211: 1 | M211: 121852 | N211: 0.097 | O211: =IF(TRIM(N211&"")="","missing",N211) -> 0.097 | P211: 121852 | Q211: 11819.64 | R211: 110032.36 | S211: 3 | T211: 161 | U211: 3.4 | V211: 2 | W211: =IF('Cleaned Data'!V211<0,"Review",'Cleaned Data'!V211) -> 2 | X211: 5 | Y211: =IFERROR('Cleaned Data'!R211/'Cleaned Data'!L211,0) -> 110032.36 | Z211: =TEXT(EV_Sales[[#This Row],[Order_Date]],"mmm-yyyy") -> Sep-2025 | AA211: =MONTH(EV_Sales[[#This Row],[Order_Date]]) -> 9 | AB211: ="Q"&ROUNDUP(MONTH(EV_Sales[[#This Row],[Order_Date]])/3,0) -> Q3
A212: EV10211 | B212: 45693 | C212: Hero Electric | D212: Photon | E212: Performance | F212: Pune | G212: Dealer | H212: Emi | I212: =IF('Cleaned Data'!H212="Emi","EMI",'Cleaned Data'!H212) -> EMI | J212: Black | K212: SP-029 | L212: 1 | M212: 123011 | N212: 0.043 | O212: =IF(TRIM(N212&"")="","missing",N212) -> 0.043 | P212: 123011 | Q212: 5289.47 | R212: 117721.53 | S212: 4 | T212: 173 | U212: 3.6 | V212: 3 | W212: =IF('Cleaned Data'!V212<0,"Review",'Cleaned Data'!V212) -> 3 | X212: 5 | Y212: =IFERROR('Cleaned Data'!R212/'Cleaned Data'!L212,0) -> 117721.53 | Z212: =TEXT(EV_Sales[[#This Row],[Order_Date]],"mmm-yyyy") -> Feb-2025 | AA212: =MONTH(EV_Sales[[#This Row],[Order_Date]]) -> 2 | AB212: ="Q"&ROUNDUP(MONTH(EV_Sales[[#This Row],[Order_Date]])/3,0) -> Q1
A213: EV10212 | B213: 45798 | C213: TVS | D213: X | E213: Performance | F213: Delhi | G213: Corporate | H213: Cash | I213: =IF('Cleaned Data'!H213="Emi","EMI",'Cleaned Data'!H213) -> Cash | J213: Green | K213: SP-003 | L213: 1 | M213: 191914 | N213: 0.035 | O213: =IF(TRIM(N213&"")="","missing",N213) -> 0.035 | P213: 191914 | Q213: 6716.99 | R213: 185197.01 | S213: 5 | T213: 199 | U213: 4.4 | V213: 10 | W213: =IF('Cleaned Data'!V213<0,"Review",'Cleaned Data'!V213) -> 10 | X213: 2 | Y213: =IFERROR('Cleaned Data'!R213/'Cleaned Data'!L213,0) -> 185197.01 | Z213: =TEXT(EV_Sales[[#This Row],[Order_Date]],"mmm-yyyy") -> May-2025 | AA213: =MONTH(EV_Sales[[#This Row],[Order_Date]]) -> 5 | AB213: ="Q"&ROUNDUP(MONTH(EV_Sales[[#This Row],[Order_Date]])/3,0) -> Q2
A214: EV10213 | B214: 46016 | C214: TVS | D214: iQube | E214: Premium | F214: Delhi | G214: Online | H214: Finance | I214: =IF('Cleaned Data'!H214="Emi","EMI",'Cleaned Data'!H214) -> Finance | J214: Grey | K214: SP-020 | L214: 2 | M214: 123749 | N214: 0.099 | O214: =IF(TRIM(N214&"")="","missing",N214) -> 0.099 | P214: 247498 | Q214: 24502.3 | R214: 222995.7 | S214: 3 | T214: 140 | U214: 4.5 | V214: 5 | W214: =IF('Cleaned Data'!V214<0,"Review",'Cleaned Data'!V214) -> 5 | X214: 2 | Y214: =IFERROR('Cleaned Data'!R214/'Cleaned Data'!L214,0) -> 111497.85 | Z214: =TEXT(EV_Sales[[#This Row],[Order_Date]],"mmm-yyyy") -> Dec-2025 | AA214: =MONTH(EV_Sales[[#This Row],[Order_Date]]) -> 12 | AB214: ="Q"&ROUNDUP(MONTH(EV_Sales[[#This Row],[Order_Date]])/3,0) -> Q4
... A244: EV10243 | B244: 45750 | C244: Ather | D244: 450S | E244: Performance | F244: Chennai | G244: Online | H244: Cash | I244: =IF('Cleaned Data'!H244="Emi","EMI",'Cleaned Data'!H244) -> Cash | J244: Blue | K244: SP-007 | L244: 2 | M244: 124300 | N244: 0.081 | O244: =IF(TRIM(N244&"")="","missing",N244) -> 0.081 | P244: 248600 | Q244: 20136.6 | R244: 228463.4 | S244: 2 | T244: 135 | U244: 3.9 | V244: 11 | W244: =IF('Cleaned Data'!V244<0,"Review",'Cleaned Data'!V244) -> 11 | X244: 2 | Y244: =IFERROR('Cleaned Data'!R244/'Cleaned Data'!L244,0) -> 114231.7 | Z244: =TEXT(EV_Sales[[#This Row],[Order_Date]],"mmm-yyyy") -> Apr-2025 | AA244: =MONTH(EV_Sales[[#This Row],[Order_Date]]) -> 4 | AB244: ="Q"&ROUNDUP(MONTH(EV_Sales[[#This Row],[Order_Date]])/3,0) -> Q2
A245: EV10244 | B245: 45760 | C245: Ola Electric | D245: S1 Pro | E245: Premium | F245: Jaipur | G245: Online | H245: Cash | I245: =IF('Cleaned Data'!H245="Emi","EMI",'Cleaned Data'!H245) -> Cash | J245: Black | K245: SP-029 | L245: 1 | M245: 131955 | O245: =IF(TRIM(N245&"")="","missing",N245) -> missing | P245: 131955 | Q245: 13063.55 | R245: 118891.45 | S245: 2 | T245: 177 | U245: 3.6 | V245: 6 | W245: =IF('Cleaned Data'!V245<0,"Review",'Cleaned Data'!V245) -> 6 | X245: 5 | Y245: =IFERROR('Cleaned Data'!R245/'Cleaned Data'!L245,0) -> 118891.45 | Z245: =TEXT(EV_Sales[[#This Row],[Order_Date]],"mmm-yyyy") -> Apr-2025 | AA245: =MONTH(EV_Sales[[#This Row],[Order_Date]]) -> 4 | AB245: ="Q"&ROUNDUP(MONTH(EV_Sales[[#This Row],[Order_Date]])/3,0) -> Q2
A246: EV10245 | B246: 45993 | C246: Ather | D246: 450S | E246: Performance | F246: Bengaluru | G246: Corporate | H246: Cash | I246: =IF('Cleaned Data'!H246="Emi","EMI",'Cleaned Data'!H246) -> Cash | J246: Green | K246: SP-030 | L246: 1 | M246: 124518 | N246: 0.049 | O246: =IF(TRIM(N246&"")="","missing",N246) -> 0.049 | P246: 124518 | Q246: 6101.38 | R246: 118416.62 | S246: 4 | T246: 197 | U246: 4.1 | V246: 10 | W246: =IF('Cleaned Data'!V246<0,"Review",'Cleaned Data'!V246) -> 10 | X246: 2 | Y246: =IFERROR('Cleaned Data'!R246/'Cleaned Data'!L246,0) -> 118416.62 | Z246: =TEXT(EV_Sales[[#This Row],[Order_Date]],"mmm-yyyy") -> Dec-2025 | AA246: =MONTH(EV_Sales[[#This Row],[Order_Date]]) -> 12 | AB246: ="Q"&ROUNDUP(MONTH(EV_Sales[[#This Row],[Order_Date]])/3,0) -> Q4
A247: EV10246 | B247: 45705 | C247: Ather | D247: 450S | E247: Commuter | F247: Mumbai | G247: Online | H247: Cash | I247: =IF('Cleaned Data'!H247="Emi","EMI",'Cleaned Data'!H247) -> Cash | J247: Grey | K247: SP-022 | L247: 1 | M247: 122964 | N247: 0.068 | O247: =IF(TRIM(N247&"")="","missing",N247) -> 0.068 | P247: 122964 | Q247: 8361.55 | R247: 114602.45 | S247: 3 | T247: 171 | U247: 4.3 | V247: 5 | W247: =IF('Cleaned Data'!V247<0,"Review",'Cleaned Data'!V247) -> 5 | X247: 2 | Y247: =IFERROR('Cleaned Data'!R247/'Cleaned Data'!L247,0) -> 114602.45 | Z247: =TEXT(EV_Sales[[#This Row],[Order_Date]],"mmm-yyyy") -> Feb-2025 | AA247: =MONTH(EV_Sales[[#This Row],[Order_Date]]) -> 2 | AB247: ="Q"&ROUNDUP(MONTH(EV_Sales[[#This Row],[Order_Date]])/3,0) -> Q1
A248: EV10247 | B248: 45878 | C248: Revolt | D248: RV1 | E248: Performance | F248: Kochi | G248: Corporate | H248: Emi | I248: =IF('Cleaned Data'!H248="Emi","EMI",'Cleaned Data'!H248) -> EMI | J248: Blue | K248: SP-030 | L248: 2 | M248: 118195 | O248: =IF(TRIM(N248&"")="","missing",N248) -> missing | P248: 236390 | Q248: 9928.38 | R248: 226461.62 | S248: 3 | T248: 156 | U248: 4 | V248: 5 | W248: =IF('Cleaned Data'!V248<0,"Review",'Cleaned Data'!V248) -> 5 | X248: 5 | Y248: =IFERROR('Cleaned Data'!R248/'Cleaned Data'!L248,0) -> 113230.81 | Z248: =TEXT(EV_Sales[[#This Row],[Order_Date]],"mmm-yyyy") -> Aug-2025 | AA248: =MONTH(EV_Sales[[#This Row],[Order_Date]]) -> 8 | AB248: ="Q"&ROUNDUP(MONTH(EV_Sales[[#This Row],[Order_Date]])/3,0) -> Q3
A249: EV10248 | B249: 45719 | C249: TVS | D249: X | E249: Commuter | F249: Kolkata | G249: Fleet | H249: Finance | I249: =IF('Cleaned Data'!H249="Emi","EMI",'Cleaned Data'!H249) -> Finance | J249: Red | K249: SP-017 | L249: 3 | M249: 178605 | N249: 0.083 | O249: =IF(TRIM(N249&"")="","missing",N249) -> 0.083 | P249: 535815 | Q249: 44472.65 | R249: 491342.35 | S249: 2 | T249: 126 | U249: 4.9 | V249: 11 | W249: =IF('Cleaned Data'!V249<0,"Review",'Cleaned Data'!V249) -> 11 | X249: 2 | Y249: =IFERROR('Cleaned Data'!R249/'Cleaned Data'!L249,0) -> 163780.78 | Z249: =TEXT(EV_Sales[[#This Row],[Order_Date]],"mmm-yyyy") -> Mar-2025 | AA249: =MONTH(EV_Sales[[#This Row],[Order_Date]]) -> 3 | AB249: ="Q"&ROUNDUP(MONTH(EV_Sales[[#This Row],[Order_Date]])/3,0) -> Q1
A250: EV10249 | B250: 45868 | C250: TVS | D250: iQube | E250: Performance | F250: Bengaluru | G250: Dealer | H250: Finance | I250: =IF('Cleaned Data'!H250="Emi","EMI",'Cleaned Data'!H250) -> Finance | J250: Red | K250: SP-010 | L250: 2 | M250: 130489 | N250: 0.037 | O250: =IF(TRIM(N250&"")="","missing",N250) -> 0.037 | P250: 260978 | Q250: 9656.19 | R250: 251321.81 | S250: 3 | T250: 167 | U250: 4.3 | V250: 2 | W250: =IF('Cleaned Data'!V250<0,"Review",'Cleaned Data'!V250) -> 2 | X250: 5 | Y250: =IFERROR('Cleaned Data'!R250/'Cleaned Data'!L250,0) -> 125660.9 | Z250: =TEXT(EV_Sales[[#This Row],[Order_Date]],"mmm-yyyy") -> Jul-2025 | AA250: =MONTH(EV_Sales[[#This Row],[Order_Date]]) -> 7 | AB250: ="Q"&ROUNDUP(MONTH(EV_Sales[[#This Row],[Order_Date]])/3,0) -> Q3
A251: EV10250 | B251: 45719 | C251: Hero Electric | D251: Optima | E251: Performance | F251: Mumbai | G251: Online | H251: Finance | I251: =IF('Cleaned Data'!H251="Emi","EMI",'Cleaned Data'!H251) -> Finance | J251: Red | K251: SP-010 | L251: 1 | M251: 105666 | N251: 0.092 | O251: =IF(TRIM(N251&"")="","missing",N251) -> 0.092 | P251: 105666 | Q251: 9721.27 | R251: 95944.73 | S251: 3 | T251: 156 | U251: 3.6 | V251: 9 | W251: =IF('Cleaned Data'!V251<0,"Review",'Cleaned Data'!V251) -> 9 | X251: 2 | Y251: =IFERROR('Cleaned Data'!R251/'Cleaned Data'!L251,0) -> 95944.73 | Z251: =TEXT(EV_Sales[[#This Row],[Order_Date]],"mmm-yyyy") -> Mar-2025 | AA251: =MONTH(EV_Sales[[#This Row],[Order_Date]]) -> 3 | AB251: ="Q"&ROUNDUP(MONTH(EV_Sales[[#This Row],[Order_Date]])/3,0) -> Q1
A252: EV10251 | B252: 45864 | C252: Bajaj | D252: Chetak Premium | E252: Premium | F252: Jaipur | G252: Corporate | H252: Emi | I252: =IF('Cleaned Data'!H252="Emi","EMI",'Cleaned Data'!H252) -> EMI | J252: Green | K252: SP-003 | L252: 2 | M252: 153278 | N252: 0.033 | O252: =IF(TRIM(N252&"")="","missing",N252) -> 0.033 | P252: 306556 | Q252: 10116.35 | R252: 296439.65 | S252: 3 | T252: 170 | U252: 4.1 | V252: 2 | W252: =IF('Cleaned Data'!V252<0,"Review",'Cleaned Data'!V252) -> 2 | X252: 3 | Y252: =IFERROR('Cleaned Data'!R252/'Cleaned Data'!L252,0) -> 148219.83 | Z252: =TEXT(EV_Sales[[#This Row],[Order_Date]],"mmm-yyyy") -> Jul-2025 | AA252: =MONTH(EV_Sales[[#This Row],[Order_Date]]) -> 7 | AB252: ="Q"&ROUNDUP(MONTH(EV_Sales[[#This Row],[Order_Date]])/3,0) -> Q3
A253: EV10252 | B253: 45786 | C253: Ampere | D253: Magnus EX | E253: Commuter | F253: Hyderabad | G253: Fleet | H253: Emi | I253: =IF('Cleaned Data'!H253="Emi","EMI",'Cleaned Data'!H253) -> EMI | J253: Green | K253: SP-024 | L253: 2 | M253: 116119 | N253: 0.066 | O253: =IF(TRIM(N253&"")="","missing",N253) -> 0.066 | P253: 232238 | Q253: 15327.71 | R253: 216910.29 | S253: 3 | T253: 176 | U253: 4.3 | V253: 11 | W253: =IF('Cleaned Data'!V253<0,"Review",'Cleaned Data'!V253) -> 11 | X253: 5 | Y253: =IFERROR('Cleaned Data'!R253/'Cleaned Data'!L253,0) -> 108455.15 | Z253: =TEXT(EV_Sales[[#This Row],[Order_Date]],"mmm-yyyy") -> May-2025 | AA253: =MONTH(EV_Sales[[#This Row],[Order_Date]]) -> 5 | AB253: ="Q"&ROUNDUP(MONTH(EV_Sales[[#This Row],[Order_Date]])/3,0) -> Q2
...

Sheet Pivot_Salesperson_Performance
A3: Row Labels | B3: Average of Customer_Rating | C3: Sum of Units_Sold | D3: Sum of Net_Sales
A4: SP-001 | B4: 4.1608696 | C4: 48 | D4: 5672955.4
A5: SP-002 | B5: 4.0826087 | C5: 37 | D5: 4218781.6
A6: SP-003 | B6: 4.0242424 | C6: 85 | D6: 10541686
A7: SP-004 | B7: 4.1590909 | C7: 46 | D7: 5399908.5
A8: SP-005 | B8: 4.2095238 | C8: 38 | D8: 4769021.2
A9: SP-006 | B9: 4.0117647 | C9: 28 | D9: 3478279.1
A10: SP-007 | B10: 3.8833333 | C10: 48 | D10: 5755963.1
A11: SP-008 | B11: 4.09375 | C11: 35 | D11: 4064335.5
A12: SP-009 | B12: 4.1095238 | C12: 43 | D12: 5450994.6
A13: SP-010 | B13: 4.2181818 | C13: 41 | D13: 5023702.3
A14: SP-011 | B14: 4.137931 | C14: 62 | D14: 7432691.6
A15: SP-012 | B15: 3.9038462 | C15: 54 | D15: 6479835.7
... A34: Grand Total | B34: 4.0982684 | C34: 1394 | D34: 1.700259e+08

Sheet Pivot_Channel_Performance
A3: Row Labels | B3: Sum of Net_Sales | C3: Sum of Units_Sold
A4: Corporate | B4: 44041221 | C4: 358
A5: Dealer | B5: 43145751 | C5: 352
A6: Fleet | B6: 41899592 | C6: 344
A7: Online | B7: 40939334 | C7: 340
A8: Grand Total | B8: 1.700259e+08 | C8: 1394

Sheet Pivot_Segment _Performance
A3: Row Labels | B3: Sum of Units_Sold
A4: Ampere | B4: 194
A5: Magnus EX | B5: 99
A6: Commuter | B6: 33
A7: Performance | B7: 36
A8: Premium | B8: 30
A9: Primus | B9: 95
A10: Commuter | B10: 31
A11: Performance | B11: 22
A12: Premium | B12: 42
A13: Ather | B13: 176
A14: 450S | B14: 65
A15: Commuter | B15: 20
... A84: Grand Total | B84: 1394

Sheet Pivot_Brand_Performance
A3: Row Labels | B3: Sum of Net_Sales | C3: Sum of Units_Sold
A4: Ampere | B4: 23523906 | C4: 194
A5: Magnus EX | B5: 10213368 | C5: 99
A6: Primus | B6: 13310538 | C6: 95
A7: Ather | B7: 22544869 | C7: 176
A8: 450S | B8: 7832619.8 | C8: 65
A9: 450X | B9: 7265587.6 | C9: 54
A10: Rizta | B10: 7446661.3 | C10: 57
A11: Bajaj | B11: 23636039 | C11: 187
A12: Chetak Premium | B12: 11208690 | C12: 79
A13: Chetak Urbane | B13: 12427349 | C13: 108
A14: Hero Electric | B14: 19049824 | C14: 183
A15: Optima | B15: 7837630.2 | C15: 80
... A30: Grand Total | B30: 1.700259e+08 | C30: 1394

Sheet Pivot_Montly_Sales
A3: Row Labels | B3: Sum of Units_Sold | C3: Sum of Net_Sales
A4: Q1 | B4: 333 | C4: 41560702
A5: 1 | B5: 128 | C5: 15726717
A6: 2 | B6: 95 | C6: 11750041
A7: 3 | B7: 110 | C7: 14083944
A8: Q2 | B8: 371 | C8: 45123934
A9: 4 | B9: 131 | C9: 15423248
A10: 5 | B10: 103 | C10: 12742849
A11: 6 | B11: 137 | C11: 16957837
A12: Q3 | B12: 330 | C12: 39755768
A13: 7 | B13: 99 | C13: 11327894
A14: 8 | B14: 123 | C14: 14864722
A15: 9 | B15: 108 | C15: 13563151
A16: Q4 | B16: 360 | C16: 43585495
A17: 10 | B17: 120 | C17: 14314723
A18: 11 | B18: 120 | C18: 15382833
A19: 12 | B19: 120 | C19: 13887939
A20: Grand Total | B20: 1394 | C20: 1.700259e+08

Sheet DASHBOARD
A1: =SUM(EV_Sales[Net_Sales]) -> 1.700259e+08
A3: =SUM(EV_Sales[Units_Sold]) -> 1394
A5: =COUNTA(EV_Sales[Order_ID]) -> 700
A7: =AVERAGE(EV_Sales[ASP]) -> 121603.07
A9: =AVERAGE(EV_Sales[Customer_Rating]) -> 4.0982684
A11: =AVERAGE(EV_Sales[Delivery_Days]) -> 7.8657143
